Workbook

Sheet Datos voluntarios
A1: N° | B1: Filial | C1: Calidad de voluntario | D1: Nombres voluntario | E1: Apellidos voluntarios | F1: RUT | G1: Fecha de ingreso | H1: Fecha nacimiento | I1: Correo | J1: Direccion | K1: Telefono | L1: Cargo | M1: Edad | N1: Edad de ingreso a CRC | O1: Antigüedad | P1: Género | Q1: Instructores de PPAA Básico | R1: Instructores de PPAA Avanzado | S1: Instructores doctrina | T1: TOT | U1: SPAC | V1: ENI | W1: CPI | X1: IM-PMER | Y1: EIEM | Z1: RIT finanzas | AA1: Podología | AB1: Matrona | AC1: TENS | AD1: Operador de salud en emergencia | AE1: Monitor ed. sexual | AF1: RCF | AG1: RIT agua | AH1: Titulo socorrista | AI1: Instructor en metodología participativa | AJ1: Supervisor en prevención de desastres | AK1: Instructor en prevención de desastres | AL1: Enfermeria
B2: Almendral | C2: Activo | D2: Lidia Ester | E2: Fontalba Guerrero | F2: 7.470.371-2 | G2: 34780 | H2: 21495 | I2: lidia.fontalbaguerrero@gmail.com | J2: Retamo # 758 | K2: 991413562 | L2: Presidente | M2: =(TODAY()-H2)/365 -> 67.142466 | N2: =(G2-H2)/365 -> 36.39726 | O2: =(TODAY()-G2)/365 -> 30.745205 | P2: F | Q2: 0 | R2: 0 | S2: 0
B3: Almendral | C3: Activo | D3: Gilda del C | E3: Gómez Aburto | F3: 7.168.729-5 | G3: 34836 | H3: 20538 | I3: gildagomez1956@gmail.com | J3: Atalaya 109 Playa Ancha | K3: 946321495 | L3: Secretario/a | M3: =(TODAY()-H3)/365 -> 69.764384 | N3: =(G3-H3)/365 -> 39.172603 | O3: =(TODAY()-G3)/365 -> 30.591781 | P3: F | Q3: 0 | R3: 0 | S3: 0
B4: Almendral | C4: Activo | D4: Karina Emilia | E4: González Espinoza | F4: 12974043-4 | G4: 43390 | H4: 27973 | I4: yzakari@hotmail.com | J4: Río Riñihue 864Viña del Mar | K4: 979980559 | L4: Director/a de Finanzas | M4: =(TODAY()-H4)/365 -> 49.394521 | N4: =(G4-H4)/365 -> 42.238356 | O4: =(TODAY()-G4)/365 -> 7.1561644 | P4: F | Q4: 0 | R4: 0 | S4: 0
B5: Almendral | C5: Activo | D5: Magda Lourdes | E5: Valle Quezada | F5: 12.845.875-1 | G5: 43390 | H5: 27532 | I5: S/I | J5: Arcilla 698 C Barón | K5: 953019125 | L5: Voluntario/a | M5: =(TODAY()-H5)/365 -> 50.60274 | N5: =(G5-H5)/365 -> 43.446575 | O5: =(TODAY()-G5)/365 -> 7.1561644 | P5: F | Q5: 0 | R5: 0 | S5: 0
B6: Almendral | C6: Activo | D6: Silvia del C | E6: Díaz Bolívar | F6: 5.016.242-7 | G6: 34801 | H6: 16800 | I6: silvitadiazbolivar@gmail.com | J6: villa Navaríno20 Miraflores | K6: 947102600 | L6: Director/a de Salud | M6: =(TODAY()-H6)/365 -> 80.005479 | N6: =(G6-H6)/365 -> 49.317808 | O6: =(TODAY()-G6)/365 -> 30.687671 | P6: F | Q6: 0 | R6: 0 | S6: 0
B7: Almendral | C7: Activo | D7: Rosa Ester | E7: Salazar Fuentealba | F7: 6.794.473-9 | G7: 44874 | H7: 19787 | I7: rosa.ester.salazar53@gmail.com | J7: San Luis 927 Placeres | K7: 996174648 | L7: Director/a de Bienestar social | M7: =(TODAY()-H7)/365 -> 71.821918 | N7: =(G7-H7)/365 -> 68.731507 | O7: =(TODAY()-G7)/365 -> 3.090411 | P7: F | Q7: 0 | R7: 0 | S7: 0
B8: Curanilahue | C8: Llamada | D8: Paz | E8: Acosta Ramírez | F8: 23.095.215-9 | G8: 45366 | H8: 40034 | I8: Pazitaacosta9@gmail.com | J8: S/I | K8: S/I | L8: Voluntario/a | M8: =(TODAY()-H8)/365 -> 16.350685 | N8: =(G8-H8)/365 -> 14.608219 | O8: =(TODAY()-G8)/365 -> 1.7424658 | P8: F | Q8: 0 | R8: 0 | S8: 0
B9: Alto Hopicio | C9: Activo | D9: Maria | E9: Gautier | F9: 14.443.487-0 | G9: 43466 | H9: 26239 | I9: S/I | J9: Alto hospicio | K9: 942787221 | M9: =(TODAY()-H9)/365 -> 54.145205 | N9: =(G9-H9)/365 -> 47.19726 | O9: =(TODAY()-G9)/365 -> 6.9479452 | P9: F
B10: Alto Hopicio | C10: Activo | D10: Carla | E10: Ortiz | F10: 19.493.798-9 | G10: 39448 | H10: 35633 | I10: S/I | J10: Alto hospicio | K10: 965016697 | M10: =(TODAY()-H10)/365 -> 28.408219 | N10: =(G10-H10)/365 -> 10.452055 | O10: =(TODAY()-G10)/365 -> 17.956164 | P10: F
B11: Alto Hopicio | C11: Activo | D11: Martha | E11: Valle | F11: 14.755.941-0 | G11: 43101 | H11: 23030 | I11: S/I | J11: Alto hospicio | K11: 987602052 | M11: =(TODAY()-H11)/365 -> 62.936986 | N11: =(G11-H11)/365 -> 54.989041 | O11: =(TODAY()-G11)/365 -> 7.9479452 | P11: F
B12: Alto Hopicio | C12: Activo | D12: Carla | E12: Arcaya | F12: 14.761.648-1 | G12: 43101 | H12: 25427 | I12: S/I | J12: Alto hospicio | K12: 991770543 | M12: =(TODAY()-H12)/365 -> 56.369863 | N12: =(G12-H12)/365 -> 48.421918 | O12: =(TODAY()-G12)/365 -> 7.9479452 | P12: F
B13: Alto Hopicio | C13: Activo | D13: Maria | E13: Canova | F13: 22.284.412-4 | G13: 42370 | H13: 28313 | I13: S/I | J13: Alto hospicio | K13: 963081766 | M13: =(TODAY()-H13)/365 -> 48.463014 | N13: =(G13-H13)/365 -> 38.512329 | O13: =(TODAY()-G13)/365 -> 9.9506849 | P13: F
B14: Alto Hopicio | C14: Activo | D14: Benjamin | E14: Neyra | F14: 22.381.707-6 | G14: 45292 | H14: 39187 | I14: S/I | J14: Alto hospicio | K14: 963081766 | M14: =(TODAY()-H14)/365 -> 18.671233 | N14: =(G14-H14)/365 -> 16.726027 | O14: =(TODAY()-G14)/365 -> 1.9452055 | P14: M
B15: Alto Hopicio | C15: Activo | D15: Daysi | E15: Saavedra | F15: 22.667.837-9 | G15: 45658 | H15: 38387 | I15: S/I | J15: Alto hospicio | K15: 923680294 | M15: =(TODAY()-H15)/365 -> 20.863014 | N15: =(G15-H15)/365 -> 19.920548 | O15: =(TODAY()-G15)/365 -> 0.94246575 | P15: F
B16: Alto Hopicio | C16: Activo | D16: Rodrigo | E16: Astorga | F16: 12.438.429-k | G16: 45292 | H16: 26841 | I16: S/I | J16: Alto hospicio | K16: 956618713 | M16: =(TODAY()-H16)/365 -> 52.49589 | N16: =(G16-H16)/365 -> 50.550685 | O16: =(TODAY()-G16)/365 -> 1.9452055 | P16: M
B17: Alto Hopicio | C17: Activo | D17: Hugo | E17: Andrade | F17: 25.481.290-0 | G17: 43101 | H17: 34728 | I17: S/I | J17: Alto hospicio | K17: 993102961 | M17: =(TODAY()-H17)/365 -> 30.887671 | N17: =(G17-H17)/365 -> 22.939726 | O17: =(TODAY()-G17)/365 -> 7.9479452 | P17: M
B18: Chillán | C18: Llamada | D18: Bárbara Mayary | E18: Acuña García | F18: 15098093-0 | G18: 39509 | H18: 30264 | I18: angelmayary@hotmail.com | J18: S/I | K18: S/I | L18: Voluntario/a | M18: =(TODAY()-H18)/365 -> 43.117808 | N18: =(G18-H18)/365 -> 25.328767 | O18: =(TODAY()-G18)/365 -> 17.789041 | P18: F | Q18: 0 | R18: 0 | S18: 0
B19: Concepción | C19: Llamada | D19: Paulina Noemi | E19: Acuña Mellado | F19: 20.154.308-8 | G19: 42892 | H19: 36233 | I19: paulinanoemi13@gma il.com | J19: Psje 5 Casa 3596, San Pedro de la Paz | K19: 9410048 75 | L19: Voluntario/a | M19: =(TODAY()-H19)/365 -> 26.764384 | N19: =(G19-H19)/365 -> 18.243836 | O19: =(TODAY()-G19)/365 -> 8.5205479 | P19: F | Q19: 0 | R19: 0 | S19: 1
B20: Lebu | C20: Llamada | D20: Danitza | E20: Aguayo Ramirez | F20: 19.364.296-9 | G20: 44592 | H20: 35461 | I20: S/I | J20: S/I | K20: S/I | L20: Voluntario/a | M20: =(TODAY()-H20)/365 -> 28.879452 | N20: =(G20-H20)/365 -> 25.016438 | O20: =(TODAY()-G20)/365 -> 3.8630137 | P20: F | Q20: 0 | R20: 0 | S20: 0
B21: Lota | C21: Llamada | D21: Juana | E21: Aguayo Salinas | F21: 12.926.126-9 | G21: 45597 | H21: 27701 | I21: S/I | J21: S/I | K21: S/I | L21: Voluntario/a | M21: =(TODAY()-H21)/365 -> 50.139726 | N21: =(G21-H21)/365 -> 49.030137 | O21: =(TODAY()-G21)/365 -> 1.109589 | P21: F | Q21: 0 | R21: 0 | S21: 0
B22: Iquique | C22: Llamada | D22: María Yaquelin | E22: Aguilar Urias | F22: 26.448.785-4 | G22: 45636 | H22: 33838 | I22: Aguilarurias.m@gmail.com | J22: S/I | K22: S/I | L22: Voluntario/a | M22: =(TODAY()-H22)/365 -> 33.326027 | N22: =(G22-H22)/365 -> 32.323288 | O22: =(TODAY()-G22)/365 -> 1.0027397 | P22: F
B23: Tocopilla | C23: Llamada | D23: Emily alejandra | E23: Aguilera pizarro | F23: 21.562.229-0 | G23: 45356 | H23: 38104 | I23: Emilyyy2004.ea39@gmail.com | J23: S/I | K23: S/I | M23: =(TODAY()-H23)/365 -> 21.638356 | N23: =(G23-H23)/365 -> 19.868493 | O23: =(TODAY()-G23)/365 -> 1.769863 | P23: F
B24: Ancud | C24: Activo | D24: MARÍA ANGÉLICA | E24: AGUAYO OJEDA | F24: 8.252.803-2 | G24: 45056 | H24: 20382 | I24: Angelica.aguayo.o@gmail.com | J24: Ancud | K24: 989730502 | M24: =(TODAY()-H24)/365 -> 70.191781 | N24: =(G24-H24)/365 -> 67.6 | O24: =(TODAY()-G24)/365 -> 2.5917808 | P24: F
B25: Ancud | C25: Activo | D25: ZILIA DEL CÁRMEN | E25: AMPUERO BARRIENTOS | F25: 7.459.810 -2 | G25: 31523 | H25: 20002 | I25: Ziliampuero1954@gmail.com | J25: Anibal Pinto N° 889 Ancud | K25: 965807436 | M25: =(TODAY()-H25)/365 -> 71.232877 | N25: =(G25-H25)/365 -> 31.564384 | O25: =(TODAY()-G25)/365 -> 39.668493 | P25: F
B26: Ancud | C26: Activo | D26: MARIA EDITH | E26: BARRIA BARRIA | F26: 7.134.883 -0 | G26: 41248 | H26: 18500 | I26: barrimaria@gmail.com | J26: Lautaro N°899 Ancud | K26: 945555863 | M26: =(TODAY()-H26)/365 -> 75.347945 | N26: =(G26-H26)/365 -> 62.323288 | O26: =(TODAY()-G26)/365 -> 13.024658 | P26: F
B27: Ancud | C27: Activo | D27: SONIA DEL CÁRMEN | E27: CARO BARRIA | F27: 7.356.910 -9 | G27: 37672 | H27: 19382 | I27: carobarriasonia@gmail.com | J27: Los Alerces N°515 Ancud | K27: 933314048 | M27: =(TODAY()-H27)/365 -> 72.931507 | N27: =(G27-H27)/365 -> 50.109589 | O27: =(TODAY()-G27)/365 -> 22.821918 | P27: F
B28: Ancud | C28: Activo | D28: MARGARITA GUADALUPE | E28: MATURANA MOLINA | F28: 7.797.067 -3 | G28: 37672 | H28: 20244 | I28: maigammm@gmail.com | J28: Prat. Pje. Oriente N°35 Ancud | K28: 997069613 | M28: =(TODAY()-H28)/365 -> 70.569863 | N28: =(G28-H28)/365 -> 47.747945 | O28: =(TODAY()-G28)/365 -> 22.821918 | P28: F
B29: Ancud | C29: Activo | D29: JENNIE DEL CÁRMEN | E29: MUÑOZ ALVARADO | F29: 8.631.300 -6 | G29: 41233 | H29: 20538 | I29: mamijennie@hotmail.com | J29: La Coruña N° 364 Ancud | K29: 988076304 | M29: =(TODAY()-H29)/365 -> 69.764384 | N29: =(G29-H29)/365 -> 56.69863 | O29: =(TODAY()-G29)/365 -> 13.065753 | P29: F
B30: Ancud | C30: Activo | D30: RUTH VERÓNICA | E30: OYARZO GALLARDO | F30: 7.851.711 -5 | G30: 44767 | H30: 21750 | I30: rveronica.oyarzog@gmail.com | J30: Los Carrera N°990 Ancud | K30: 966375661 | M30: =(TODAY()-H30)/365 -> 66.443836 | N30: =(G30-H30)/365 -> 63.060274 | O30: =(TODAY()-G30)/365 -> 3.3835616 | P30: F
B31: Ancud | C31: Activo | D31: MARIA ALONDRA | E31: REUTER MIRANDA | F31: 6.681.789 -k | G31: 31030 | H31: 18130 | I31: aluette@live.com | J31: Errazuriz N° 350 Ancud | K31: 966048985 | M31: =(TODAY()-H31)/365 -> 76.361644 | N31: =(G31-H31)/365 -> 35.342466 | O31: =(TODAY()-G31)/365 -> 41.019178 | P31: F
B32: Ancud | C32: Activo | D32: REBECA AYDE | E32: SANTANA DÍAZ | F32: 8.258.583 -4 | G32: 45056 | H32: 20110 | I32: rebecasantana55@gmail.com | J32: Ancud | K32: 988003435 | M32: =(TODAY()-H32)/365 -> 70.936986 | N32: =(G32-H32)/365 -> 68.345205 | O32: =(TODAY()-G32)/365 -> 2.5917808 | P32: F
B33: SR Atacama Coquimbo | C33: Llamada | D33: Josefa | E33: Aguirre Varas | F33: 22.957.475-2 | G33: 45061 | H33: 39871 | I33: Jo.bts.2009@gmail.com | J33: S/I | K33: S/I | L33: Voluntario/a | M33: =(TODAY()-H33)/365 -> 16.79726 | N33: =(G33-H33)/365 -> 14.219178 | O33: =(TODAY()-G33)/365 -> 2.5780822 | P33: F | Q33: 0 | R33: 0 | S33: 0
B34: Nancagua | C34: Llamada | D34: Gabriel | E34: Ahumada Diaz | F34: 14.302.685-k | G34: 44848 | H34: S/I | I34: S/I | J34: S/I | K34: S/I | M34: =(TODAY()-H34)/365 -> #VALUE! | N34: =(G34-H34)/365 -> #VALUE! | O34: =(TODAY()-G34)/365 -> 3.1616438 | P34: M
B35: Angol | C35: Activo | D35: Sonia del Carmen | E35: Saldias Meza | F35: 7.265.289-4 | G35: 28978 | H35: 21074 | I35: snsaldias@gmail.com | J35: Pampa Graneros 1506 | K35: 942927464 | L35: Voluntario/a | M35: =(TODAY()-H35)/365 -> 68.29589 | N35: =(G35-H35)/365 -> 21.654795 | O35: =(TODAY()-G35)/365 -> 46.641096 | P35: F | Q35: 0 | R35: 0 | S35: 0
B36: Angol | C36: Activo | D36: Ruby Nelly | E36: Aguirre Pineda | F36: 9.789.296-7 | G36: 32588 | H36: 24034 | I36: rubynellyaguirrep@gmail.com | J36: Amancay 1242 | K36: 949186075 | L36: Voluntario/a | M36: =(TODAY()-H36)/365 -> 60.186301 | N36: =(G36-H36)/365 -> 23.435616 | O36: =(TODAY()-G36)/365 -> 36.750685 | P36: F | Q36: 0 | R36: 0 | S36: 0
B37: Parral | C37: Llamada | D37: Sara María José | E37: Ahumada Placencio | F37: S/I | G37: S/I | H37: S/I | I37: S/I | J37: S/I | K37: S/I | L37: Director/a de Salud | O37: =(TODAY()-G37)/365 -> #VALUE! | P37: F | Q37: 0 | R37: 0 | S37: 0
B38: Loncoche | C38: Llamada | D38: Paula | E38: Aichele C. | F38: 21.645.926-1 | G38: 44867 | H38: S/I | I38: S/I | J38: S/I | K38: 9985720 42 | L38: Director/a de Comunicaciones | M38: 0 | O38: =(TODAY()-G38)/365 -> 3.109589 | P38: F | Q38: 0 | R38: 0 | S38: 0
B39: Talagante | C39: Llamada | D39: Antonia Millaray | E39: Alarcon Nuñez | F39: 20.985.936-K | G39: 43112 | H39: 37330 | I39: antonia.alarcon2020@umce.cl | J39: Arturo Prat 1039 Talagante | K39: 991424570 | M39: =(TODAY()-H39)/365 -> 23.758904 | N39: =(G39-H39)/365 -> 15.841096 | O39: =(TODAY()-G39)/365 -> 7.9178082 | P39: F
B40: Angol | C40: Activo | D40: Rosalbina del Carmen | E40: Campos Paredes | F40: 6.841.520-9 | G40: 30302 | H40: 20321 | I40: S/I | J40: General Lagos 286 | K40: 995133160 | L40: Voluntario/a | M40: =(TODAY()-H40)/365 -> 70.358904 | N40: =(G40-H40)/365 -> 27.345205 | O40: =(TODAY()-G40)/365 -> 43.013699 | P40: F | Q40: 0 | R40: 0 | S40: 0
B41: Angol | C41: Activo | D41: Sylvia | E41: Rivas Campos | F41: 7.051.880-5 | G41: 29694 | H41: 19692 | I41: Sylviarivas29@gmail.com | J41: Andalien 778 | K41: 989063569 | L41: Voluntario/a | M41: =(TODAY()-H41)/365 -> 72.082192 | N41: =(G41-H41)/365 -> 27.40274 | O41: =(TODAY()-G41)/365 -> 44.679452 | P41: F | Q41: 0 | R41: 0 | S41: 0
B42: SR Araucanía | C42: Llamada | D42: Carolina | E42: Alarcon Perez | F42: 12.386.893-5 | G42: 45409 | H42: 26972 | I42: carolina7alarpe@gmail. com | J42: S/I | K42: S/I | L42: Voluntario/a | M42: =(TODAY()-H42)/365 -> 52.136986 | N42: =(G42-H42)/365 -> 50.512329 | O42: =(TODAY()-G42)/365 -> 1.6246575 | P42: F | Q42: 0 | R42: 0 | S42: 0
B43: Tocopilla | C43: Llamada | D43: Rocío dianne | E43: Albayay camposano | F43: 14.930.865-2 | G43: 41318 | H43: S/I | I43: S/I | J43: S/I | K43: S/I | N43: =(G43-H43)/365 -> #VALUE! | O43: =(TODAY()-G43)/365 -> 12.832877 | P43: F
B44: Coquimbo | C44: Llamada | D44: Veronica | E44: Alcayaga Nuñez | F44: 6.815.106-6 | G44: S/I | H44: 20639 | I44: veronicaalcayaga@gmail.com | J44: S/I | K44: S/I | L44: Voluntario/a | M44: =(TODAY()-H44)/365 -> 69.487671 | N44: S/I | O44: =(TODAY()-G44)/365 -> #VALUE! | P44: F | Q44: 0 | R44: 0 | S44: 0
B45: Reumén | C45: Llamada | D45: Dilverd | E45: Alvarado Flores | F45: 13.814.516-6 | G45: 44535 | H45: 29529 | I45: S/I | J45: S/I | K45: S/I | L45: Voluntario/a | M45: =(TODAY()-H45)/365 -> 45.131507 | N45: =(G45-H45)/365 -> 41.112329 | O45: =(TODAY()-G45)/365 -> 4.0191781 | P45: M | Q45: 0 | R45: 0 | S45: 0
B46: Angol | C46: Activo | D46: Flor América | E46: Medina Viveros | F46: 6.131.841-0 | G46: 30419 | H46: 17124 | I46: S/I | J46: Israel Roa 292 | K46: 984673051 | L46: Voluntario/a | M46: =(TODAY()-H46)/365 -> 79.117808 | N46: =(G46-H46)/365 -> 36.424658 | O46: =(TODAY()-G46)/365 -> 42.693151 | P46: F | Q46: 0 | R46: 0 | S46: 0
B47: La Serena | C47: Llamada | D47: Maria Jose | E47: Alvarez | F47: 21.403.903-6 | G47: 44777 | H47: 37895 | I47: S/I | J47: S/I | K47: S/I | L47: Voluntario/a | M47: =(TODAY()-H47)/365 -> 22.210959 | N47: =(G47-H47)/365 -> 18.854795 | O47: =(TODAY()-G47)/365 -> 3.3561644 | P47: F | Q47: 0 | R47: 0 | S47: 0
B48: Angol | C48: Llamada | D48: Nelly del Carmen | E48: Álvarez Figueroa | F48: 6.478.495-1 | G48: 45266 | H48: 20066 | I48: nellytadelcarmen@hotmail,com | J48: S/I | K48: S/I | L48: Voluntario/a | M48: =(TODAY()-H48)/365 -> 71.057534 | N48: =(G48-H48)/365 -> 69.041096 | O48: =(TODAY()-G48)/365 -> 2.0164384 | P48: F | Q48: 0 | R48: 0 | S48: 0
B49: Angol | C49: Activo | D49: Nancy Fabiola | E49: Pezo Salazar | F49: 10.199.192- k | G49: 38126 | H49: 24050 | I49: npezosalazar@gmail.com | J49: Colipi 157 | K49: 978045000 | L49: Vicepresidente | M49: =(TODAY()-H49)/365 -> 60.142466 | N49: =(G49-H49)/365 -> 38.564384 | O49: =(TODAY()-G49)/365 -> 21.578082 | P49: F | Q49: 0 | R49: 0 | S49: 0
B50: Angol | C50: Activo | D50: Ruth Erika | E50: León Jara | F50: 9.505.956-2 | G50: 37386 | H50: 22783 | I50: rutherikaleon@gmail.com | J50: Nahuelbuta 171 | K50: 98842205 | L50: Voluntario/a | M50: =(TODAY()-H50)/365 -> 63.613699 | N50: =(G50-H50)/365 -> 40.008219 | O50: =(TODAY()-G50)/365 -> 23.605479 | P50: F | Q50: 0 | R50: 0 | S50: 0
B51: Angol | C51: Activo | D51: Lucia Brigida | E51: Canales Canales | F51: 9.048.639-k | G51: 37545 | H51: 22746 | I51: Lucia.canalescanales@gmail.c om | J51: Monte Sinaí 2385 | K51: 931926001 | L51: Voluntario/a | M51: =(TODAY()-H51)/365 -> 63.715068 | N51: =(G51-H51)/365 -> 40.545205 | O51: =(TODAY()-G51)/365 -> 23.169863 | P51: F | Q51: 0 | R51: 0 | S51: 0
B52: Angol | C52: Activo | D52: Herminda del Carmen | E52: Martínez Salgado | F52: 5.355.342-7 | G52: 30145 | H52: 15241 | I52: hermindamartinezsalgado@ gmail.com | J52: Ilabaca 381 | K52: 93119601 | L52: Director/a de Comunicaciones | M52: =(TODAY()-H52)/365 -> 84.276712 | N52: =(G52-H52)/365 -> 40.832877 | O52: =(TODAY()-G52)/365 -> 43.443836 | P52: F | Q52: 0 | R52: 0 | S52: 0
B53: Lota | C53: Llamada | D53: Bernarda | E53: Alvear Espinoza | F53: 15.158.919-7 | G53: 45597 | H53: 30785 | I53: Bernardaalvear123@ gmail.com | J53: S/I | K53: S/I | L53: Voluntario/a | M53: =(TODAY()-H53)/365 -> 41.690411 | N53: =(G53-H53)/365 -> 40.580822 | O53: =(TODAY()-G53)/365 -> 1.109589 | P53: F | Q53: 0 | R53: 0 | S53: 0
B54: Angol | C54: Activo | D54: Juana Mónica | E54: Arévalo Oyarzo | F54: 6.323.847-3 | G54: 33725 | H54: 17360 | I54: Arevalojuana52@gmail.com | J54: Nueva Rancagua 202 | K54: 956444330 | L54: Director/a de Bienestar social | M54: =(TODAY()-H54)/365 -> 78.471233 | N54: =(G54-H54)/365 -> 44.835616 | O54: =(TODAY()-G54)/365 -> 33.635616 | P54: F | Q54: 0 | R54: 0 | S54: 0
B55: Chillán | C55: Llamada | D55: Camila Fernanda | E55: Alviz Padilla | F55: 18.431.534 -3 | G55: 41036 | H55: 34313 | I55: camila.alviz93@gmail.com | J55: S/I | K55: S/I | L55: Voluntario/a | M55: =(TODAY()-H55)/365 -> 32.024658 | N55: =(G55-H55)/365 -> 18.419178 | O55: =(TODAY()-G55)/365 -> 13.605479 | P55: F | Q55: 0 | R55: 0 | S55: 0
B56: Angol | C56: Activo | D56: Eliana | E56: Valencia Alarcón | F56: 9.330.290-7 | G56: 38617 | H56: 21419 | I56: S/I | J56: Ruta 180 | K56: 977470401 | L56: Voluntario/a | M56: =(TODAY()-H56)/365 -> 67.350685 | N56: =(G56-H56)/365 -> 47.117808 | O56: =(TODAY()-G56)/365 -> 20.232877 | P56: F | Q56: 0 | R56: 0 | S56: 0
B57: Angol | C57: Activo | D57: María Elvira | E57: Beltrán González | F57: 7.296.251-6 | G57: 37026 | H57: 19300 | I57: Elvira.beltran@gmail.com | J57: Los Andes 098 | K57: 999370454 | L57: Voluntario/a | M57: =(TODAY()-H57)/365 -> 73.156164 | N57: =(G57-H57)/365 -> 48.564384 | O57: =(TODAY()-G57)/365 -> 24.591781 | P57: F | Q57: 0 | R57: 0 | S57: 0
B58: Viña Del Mar | C58: Llamada | D58: Mario | E58: Anatibia Illanes | F58: S/I | G58: 41640 | H58: S/I | I58: S/I | J58: S/I | K58: S/I | L58: Voluntario/a | O58: =(TODAY()-G58)/365 -> 11.950685 | P58: M | Q58: 0 | R58: 0 | S58: 0
B59: Angol | C59: Activo | D59: Myriam Ruth | E59: Cares Fuentes | F59: 8.975.429-1 | G59: 42357 | H59: 23018 | I59: Myriam.mrc65@gmail.com | J59: Quebrada Onda 204 | K59: 984429676 | L59: Director/a de Gestión del Riesgo | M59: =(TODAY()-H59)/365 -> 62.969863 | N59: =(G59-H59)/365 -> 52.983562 | O59: =(TODAY()-G59)/365 -> 9.9863014 | P59: F | Q59: 0 | R59: 0 | S59: 0
B60: La Serena | C60: Llamada | D60: Martina | E60: Andonaire Rodriguez | F60: 21.575.133-3 | G60: 44879 | H60: 38130 | I60: Martina.rsole@gmail.com | J60: S/I | K60: S/I | L60: Voluntario/a | M60: =(TODAY()-H60)/365 -> 21.567123 | N60: =(G60-H60)/365 -> 18.490411 | O60: =(TODAY()-G60)/365 -> 3.0767123 | P60: F | Q60: 0 | R60: 0 | S60: 0
B61: Angol | C61: Activo | D61: José Eufracio | E61: Maldonado Bustos | F61: 6.752.400-4 | G61: 41519 | H61: 19843 | I61: jeumaldonado@hotmail. com | J61: Lientur 1051 | K61: 987515358 | L61: Director/a de Finanzas | M61: =(TODAY()-H61)/365 -> 71.668493 | N61: =(G61-H61)/365 -> 59.386301 | O61: =(TODAY()-G61)/365 -> 12.282192 | P61: F | Q61: 0 | R61: 0 | S61: 0
B62: Punta Arenas | C62: Llamada | D62: Nilia | E62: Andrade Paillacán | F62: 15.309.192-7 | G62: 45200 | H62: 30036 | I62: Niliaa.podologaclinica@outlook.cl | J62: S/I | K62: S/I | M62: =(TODAY()-H62)/365 -> 43.742466 | N62: =(G62-H62)/365 -> 41.545205 | O62: =(TODAY()-G62)/365 -> 2.1972603 | P62: F
B63: Angol | C63: Activo | D63: Guicela Noemi | E63: Castro Figueroa | F63: 6.685.519-8 | G63: 41048 | H63: 18692 | I63: Guicela1951gmail.com | J63: Los Alerces 871 | K63: 981564090 | L63: Director/a de Desarrollo | M63: =(TODAY()-H63)/365 -> 74.821918 | N63: =(G63-H63)/365 -> 61.249315 | O63: =(TODAY()-G63)/365 -> 13.572603 | P63: F | Q63: 0 | R63: 0 | S63: 0
B64: Lican Ray | C64: Llamada | D64: Maria Belen | E64: Angelbeck Villablanca | F64: 19.608.471-1 | G64: 45215 | H64: 35704 | I64: S/I | J64: S/I | K64: S/I | L64: Voluntario/a | M64: =(TODAY()-H64)/365 -> 28.213699 | N64: =(G64-H64)/365 -> 26.057534 | O64: =(TODAY()-G64)/365 -> 2.1561644 | P64: F | Q64: 0 | R64: 0 | S64: 0
B65: Angol | C65: Activo | D65: Silvia Lady | E65: Pereira Fonseca | F65: 6.271-694-0 | G65: 43041 | H65: 19357 | I65: Pereirasilvia1952@gmail.com | J65: Aulen3153 | K65: 998354197 | L65: Secretario/a | M65: =(TODAY()-H65)/365 -> 73 | N65: =(G65-H65)/365 -> 64.887671 | O65: =(TODAY()-G65)/365 -> 8.1123288 | P65: F | Q65: 0 | R65: 0 | S65: 0
B66: Los Ángeles | C66: Llamada | D66: Carolina | E66: Arancibia | F66: 21472664-5 | G66: 44403 | H66: 37984 | I66: S/I | J66: S/I | K66: S/I | L66: Voluntario/a | M66: =(TODAY()-H66)/365 -> 21.967123 | N66: =(G66-H66)/365 -> 17.586301 | O66: =(TODAY()-G66)/365 -> 4.3808219 | P66: F | Q66: 0 | R66: 0 | S66: 0
B67: Angol | C67: Activo | D67: Ruth Leonor a | E67: Carrillo Carriel | F67: 7.305.507-5 | G67: 43319 | H67: 19627 | I67: Leonora.carriel@gmail.com | J67: Esmeralda 0313 | K67: 952305345 | L67: Director/a de Salud | M67: =(TODAY()-H67)/365 -> 72.260274 | N67: =(G67-H67)/365 -> 64.909589 | O67: =(TODAY()-G67)/365 -> 7.3506849 | P67: F | Q67: 0 | R67: 0 | S67: 0
B68: Angol | C68: Activo | D68: Alejandro Itamar | E68: Fernández Arriagada | F68: 5.793.097-7 | G68: 42737 | H68: 18376 | I68: Afernandez811@gmail.com | J68: Los Alerces 871 | K68: 952077688 | L68: Presidente | M68: =(TODAY()-H68)/365 -> 75.687671 | N68: =(G68-H68)/365 -> 66.742466 | O68: =(TODAY()-G68)/365 -> 8.9452055 | P68: F | Q68: 0 | R68: 0 | S68: 1
B69: Los Ángeles | C69: Llamada | D69: Isidora | E69: Arancibia | F69: 21865405-4 | G69: S/I | H69: 38513 | I69: S/I | J69: S/I | K69: S/I | L69: Voluntario/a | M69: =(TODAY()-H69)/365 -> 20.517808 | N69: S/I | O69: =(TODAY()-G69)/365 -> #VALUE! | P69: F | Q69: 0 | R69: 0 | S69: 0
B70: Maipú | C70: Llamada | D70: Bárbara | E70: Aravena | F70: 18.905.396-7 | G70: S/I | H70: 33118 | I70: S/I | J70: S/I | K70: S/I | L70: Voluntario/a | M70: =(TODAY()-H70)/365 -> 35.29863 | N70: S/I | O70: =(TODAY()-G70)/365 -> #VALUE! | P70: F | Q70: 0 | R70: 0 | S70: 0
B71: Curanilahue | C71: Llamada | D71: Edgardo | E71: Aravena Guzmán | F71: 21.337.486-9 | G71: 45366 | H71: 37789 | I71: edgardoaravenaguzman@gmail.com | J71: S/I | K71: S/I | L71: Voluntario/a | M71: =(TODAY()-H71)/365 -> 22.50137 | N71: =(G71-H71)/365 -> 20.758904 | O71: =(TODAY()-G71)/365 -> 1.7424658 | P71: M | Q71: 0 | R71: 0 | S71: 0
B72: San Miguel | C72: Llamada | D72: Elias | E72: Arce | F72: 6.241.033-7 | G72: 44328 | H72: 17954 | I72: S/I | J72: S/I | K72: S/I | L72: Voluntario/a | M72: =(TODAY()-H72)/365 -> 76.843836 | N72: =(G72-H72)/365 -> 72.257534 | O72: =(TODAY()-G72)/365 -> 4.5863014 | P72: F | Q72: 0 | R72: 0 | S72: 0
B73: Mejillones | C73: Llamada | D73: Cecilia Alejandra | E73: Arce Muñoz | F73: 15.088.835-2 | G73: 41125 | H73: 30224 | I73: Cecilia.arce.ventas@gmail.com | J73: S/I | K73: S/I | L73: Voluntario/a | M73: =(TODAY()-H73)/365 -> 43.227397 | N73: =(G73-H73)/365 -> 29.865753 | O73: =(TODAY()-G73)/365 -> 13.361644 | P73: F | Q73: 0 | R73: 0 | S73: 0
B74: Constitución | C74: Llamada | D74: Diego | E74: Ardiles Montero | F74: 20.940.849-k | G74: 44828 | H74: 37165 | I74: S/I | J74: S/I | K74: S/I | M74: =(TODAY()-H74)/365 -> 24.210959 | N74: =(G74-H74)/365 -> 20.994521 | O74: =(TODAY()-G74)/365 -> 3.2164384 | P74: M
B75: Antofagasta | C75: Activo | D75: Valerie | E75: Vargas Ordoñez | F75: 25.647.236-8 | G75: 45458 | H75: 38993 | I75: S/I | J75: Calle Valdivia 3447, Depto 203 | K75: 946963880 | L75: Voluntario/a | M75: =(TODAY()-H75)/365 -> 19.20274 | N75: =(G75-H75)/365 -> 17.712329 | O75: =(TODAY()-G75)/365 -> 1.490411 | P75: F | Q75: 0 | R75: 0 | S75: 0
B76: Antofagasta | C76: Activo | D76: Paz | E76: Olivares Ponce | F76: 20.262.247-k | G76: 43767 | H76: 36651 | I76: S/I | J76: mariano farandato #1155 | K76: 973980541 | L76: Voluntario/a | M76: =(TODAY()-H76)/365 -> 25.619178 | N76: =(G76-H76)/365 -> 19.49589 | O76: =(TODAY()-G76)/365 -> 6.1232877 | P76: F | Q76: 0 | R76: 0 | S76: 0
B77: Puente Alto | C77: Llamada | D77: Elias | E77: Arias Herrera | F77: 21.010.657-K | G77: 42497 | H77: 39581 | I77: Arias.elias.h@gmail.com | J77: S/I | K77: S/I | M77: =(TODAY()-H77)/365 -> 17.591781 | N77: =(G77-H77)/365 -> 7.9890411 | O77: =(TODAY()-G77)/365 -> 9.6027397 | P77: M
B78: Antofagasta | C78: Activo | D78: Francisca | E78: Zarricueta Rivera | F78: 21.126.549-3 | G78: 45444 | H78: 37495 | I78: S/I | J78: Las Pataguas 8351 | K78: 955170785 | L78: Voluntario/a | M78: =(TODAY()-H78)/365 -> 23.306849 | N78: =(G78-H78)/365 -> 21.778082 | O78: =(TODAY()-G78)/365 -> 1.5287671 | P78: F | Q78: 0 | R78: 0 | S78: 0
B79: Antofagasta | C79: Activo | D79: John | E79: Aguirre Aguirre | F79: 19.843.640-2 | G79: 45584 | H79: 35812 | I79: S/I | J79: mariano farandato #1155 | K79: 957612463 | L79: Voluntario/a | M79: =(TODAY()-H79)/365 -> 27.917808 | N79: =(G79-H79)/365 -> 26.772603 | O79: =(TODAY()-G79)/365 -> 1.1452055 | P79: M | Q79: 0 | R79: 0 | S79: 0
B80: Tolten | C80: Llamada | D80: Paloma | E80: Arnaiz | F80: 17265936-5 | G80: 45146 | H80: 32647 | I80: S/I | J80: S/I | K80: 958445382 | L80: Voluntario/a | M80: =(TODAY()-H80)/365 -> 36.589041 | N80: =(G80-H80)/365 -> 34.243836 | O80: =(TODAY()-G80)/365 -> 2.3452055 | P80: F | Q80: 0 | R80: 0 | S80: 0
B81: Esmeralda Colina | C81: Llamada | D81: Ignacio | E81: Arriagada | F81: 21.685.217-6 | G81: 44044 | H81: 36739 | I81: S/I | J81: S/I | K81: S/I | L81: Voluntario/a | M81: =(TODAY()-H81)/365 -> 25.378082 | N81: =(G81-H81)/365 -> 20.013699 | O81: =(TODAY()-G81)/365 -> 5.3643836 | P81: M | Q81: 0 | R81: 0 | S81: 0
B82: Antofagasta | C82: Activo | D82: Hernes | E82: Puentes Vargas | F82: 17.094.072-5 | G82: 43767 | H82: 32645 | I82: S/I | J82: Pasaje esmeralda | K82: 992925671 | L82: Director/a de Gestión del Riesgo | M82: =(TODAY()-H82)/365 -> 36.594521 | N82: =(G82-H82)/365 -> 30.471233 | O82: =(TODAY()-G82)/365 -> 6.1232877 | P82: M | Q82: 0 | R82: 0 | S82: 0
B83: Antofagasta | C83: Activo | D83: Juana | E83: Riquelme Narváez | F83: 5.671.216-K | G83: 28536 | H83: 17045 | I83: S/I | J83: Llanquihue 4174 | K83: 957824417 | L83: Voluntario/a | M83: =(TODAY()-H83)/365 -> 79.334247 | N83: =(G83-H83)/365 -> 31.482192 | O83: =(TODAY()-G83)/365 -> 47.852055 | P83: F | Q83: 0 | R83: 0 | S83: 0
B84: Antofagasta | C84: Activo | D84: Eva | E84: Coaquira Guerra | F84: 24.309.815-7 | G84: 45444 | H84: 33732 | I84: S/I | J84: Orella 827 | K84: 975234820 | L84: Voluntario/a | M84: =(TODAY()-H84)/365 -> 33.616438 | N84: =(G84-H84)/365 -> 32.087671 | O84: =(TODAY()-G84)/365 -> 1.5287671 | P84: F | Q84: 0 | R84: 0 | S84: 0
B85: Pozo Almonte | C85: Llamada | D85: Soledad | E85: Arriagada | F85: 7.118.157-6 | G85: 43535 | H85: 21098 | I85: S/I | J85: S/I | K85: S/I | L85: Voluntario/a | M85: =(TODAY()-H85)/365 -> 68.230137 | N85: =(G85-H85)/365 -> 61.471233 | O85: =(TODAY()-G85)/365 -> 6.7589041 | P85: F
B86: Antofagasta | C86: Activo | D86: Danilo | E86: Gómez Castillo | F86: 13.870.008-9 | G86: 42586 | H86: 29121 | I86: S/I | J86: Calle Los Morros 1520 | K86: 933835716 | L86: Presidente | M86: =(TODAY()-H86)/365 -> 46.249315 | N86: =(G86-H86)/365 -> 36.890411 | O86: =(TODAY()-G86)/365 -> 9.3589041 | P86: M | Q86: 1 | R86: 1 | S86: 0 | V86: 1
B87: Antofagasta | C87: Activo | D87: Haydee | E87: Bernal Menares | F87: 8.550.139-9 | G87: 38090 | H87: 22432 | I87: S/I | J87: Guayaquil 1498 | K87: 988060022 | L87: Director/a de Finanzas | M87: =(TODAY()-H87)/365 -> 64.575342 | N87: =(G87-H87)/365 -> 42.89863 | O87: =(TODAY()-G87)/365 -> 21.676712 | P87: F | Q87: 0 | R87: 0 | S87: 0
B88: Antofagasta | C88: Activo | D88: Elizabeth | E88: Tapia Dominguez | F88: 7.001.879-9 | G88: 35046 | H88: 19381 | I88: S/I | J88: Julio Montt 7946 | K88: 995947610 | L88: Voluntario/a | M88: =(TODAY()-H88)/365 -> 72.934247 | N88: =(G88-H88)/365 -> 42.917808 | O88: =(TODAY()-G88)/365 -> 30.016438 | P88: F | Q88: 0 | R88: 0 | S88: 0
B89: Antofagasta | C89: Activo | D89: Ronald | E89: Vargas Ordoñez | F89: 25.809.019-5 | G89: 37345 | H89: S/I | I89: S/I | J89: Avda Antilhue #01350 | K89: 967348244 | L89: Voluntario/a | M89: 0 | O89: =(TODAY()-G89)/365 -> 23.717808 | P89: M | Q89: 0 | R89: 0 | S89: 0
B90: Antofagasta | C90: Activo | D90: Yerall | E90: Muñoz Olivares | F90: 22.263.774-0 | G90: 39011 | H90: S/I | I90: S/I | J90: Avda Antilhue #01350 | K90: 931811390 | L90: Voluntario/a | M90: 0 | O90: =(TODAY()-G90)/365 -> 19.153425 | P90: F | Q90: 0 | R90: 0 | S90: 0
B91: Antofagasta | C91: Activo | D91: Victor | E91: Adrian Monardes | F91: 19.395.961-K | G91: 35185 | H91: S/I | I91: S/I | J91: Avda Bonilla 9377 | K91: 962738921 | L91: Voluntario/a | M91: 0 | O91: =(TODAY()-G91)/365 -> 29.635616 | P91: M | Q91: 0 | R91: 0 | S91: 0
B92: Antofagasta | C92: Activo | D92: Juana | E92: Esquivel Ramirez | F92: 8.764.837-0 | G92: 38019 | H92: 21637 | I92: S/I | J92: Leonardo Da Vinci 753 | K92: 993899583 | L92: Voluntario/a | M92: =(TODAY()-H92)/365 -> 66.753425 | N92: =(G92-H92)/365 -> 44.882192 | O92: =(TODAY()-G92)/365 -> 21.871233 | P92: F | Q92: 0 | R92: 0 | S92: 0
B93: Antofagasta | C93: Activo | D93: Hitamar | E93: Santibáñez González | F93: 8.815.482-7 | G93: 38813 | H93: 22306 | I93: S/I | J93: Bonilla 9375 | K93: 923972872 | L93: Voluntario/a | M93: =(TODAY()-H93)/365 -> 64.920548 | N93: =(G93-H93)/365 -> 45.224658 | O93: =(TODAY()-G93)/365 -> 19.69589 | P93: F | Q93: 0 | R93: 0 | S93: 0
B94: Antofagasta | C94: Activo | D94: Luisa | E94: Navarrete Cortes | F94: 8.142.504-3 | G94: 38788 | H94: 21701 | I94: S/I | J94: Mexico 1771 | K94: 988368657 | L94: Director/a de Bienestar social | M94: =(TODAY()-H94)/365 -> 66.578082 | N94: =(G94-H94)/365 -> 46.813699 | O94: =(TODAY()-G94)/365 -> 19.764384 | P94: F | Q94: 0 | R94: 0 | S94: 0
B95: Antofagasta | C95: Activo | D95: Clara | E95: Soza Rios | F95: 6.585429-5 | G95: 37376 | H95: 19948 | I95: S/I | J95: Calle Mexico 1128 | K95: 981983282 | L95: Secretario/a | M95: =(TODAY()-H95)/365 -> 71.380822 | N95: =(G95-H95)/365 -> 47.747945 | O95: =(TODAY()-G95)/365 -> 23.632877 | P95: F | Q95: 0 | R95: 0 | S95: 0
B96: Antofagasta | C96: Activo | D96: Edita | E96: Lara Bushnahe | F96: 12.373.961-2 | G96: 44351 | H96: 26911 | I96: S/I | J96: Calle Adamson 3590 | K96: 985570270 | L96: Voluntario/a | M96: =(TODAY()-H96)/365 -> 52.30411 | N96: =(G96-H96)/365 -> 47.780822 | O96: =(TODAY()-G96)/365 -> 4.5232877 | P96: F | Q96: 0 | R96: 0 | S96: 0
B97: Antofagasta | C97: Activo | D97: Pilar | E97: Ordoñez Ordoñez | F97: 25.455.517-7 | G97: 45458 | H97: 27991 | I97: S/I | J97: Avda Antilhue #01350 | K97: 946963880 | L97: Voluntario/a | M97: =(TODAY()-H97)/365 -> 49.345205 | N97: =(G97-H97)/365 -> 47.854795 | O97: =(TODAY()-G97)/365 -> 1.490411 | P97: F | Q97: 0 | R97: 0 | S97: 0
B98: Antofagasta | C98: Activo | D98: Rosa | E98: Rodriguez Vargas | F98: 5.688.811-k | G98: 33686 | H98: 16009 | I98: S/I | J98: Pasaje Río Palena 1466 Villa el Mirador | K98: 997409087 | L98: Voluntario/a | M98: =(TODAY()-H98)/365 -> 82.172603 | N98: =(G98-H98)/365 -> 48.430137 | O98: =(TODAY()-G98)/365 -> 33.742466 | P98: F | Q98: 0 | R98: 0 | S98: 0
B99: Antofagasta | C99: Activo | D99: Virna | E99: Angel Butt | F99: 11.506.783-4 | G99: 44951 | H99: 25858 | I99: S/I | J99: Avda Antilhue #01350 | K99: 957708413 | L99: Voluntario/a | M99: =(TODAY()-H99)/365 -> 55.189041 | N99: =(G99-H99)/365 -> 52.309589 | O99: =(TODAY()-G99)/365 -> 2.8794521 | P99: F | Q99: 0 | R99: 0 | S99: 0
B100: Antofagasta | C100: Activo | D100: José Nibaldo | E100: Castillo Araya | F100: 6.097.494-2 | G100: 37834 | H100: 18567 | I100: S/I | J100: Av. Andrés Sabella Gálvez 3194-A | K100: 963933500 | L100: Voluntario/a | M100: =(TODAY()-H100)/365 -> 75.164384 | N100: =(G100-H100)/365 -> 52.786301 | O100: =(TODAY()-G100)/365 -> 22.378082 | P100: M | Q100: 0 | R100: 0 | S100: 0
...

Sheet Datos filial
A1: N° | B1: Filial | C1: Sede regional | D1: Voluntarios activos | E1: Voluntarios de llamada | F1: RUT | G1: Dirección | H1: Teléfono contacto | I1: Fecha ultima elecciones | J1: Instagram | K1: Tiene al menos una red social? | L1: Persona dedicada a redes | M1: Cambiar uniforme ceremonial | N1: Cambiar Color azul Chaquetas gestión del riesgo | O1: Voluntarios sin capacitación | P1: Voluntarios sin PPAA | Q1: Voluntarios sin Doctrina | R1: Voluntarios con título específico | S1: Instructores de PPAA | T1: Instructores doctrina | U1: Club adulto mayor | V1: Res. San. Policlinico | W1: Acción migratoria | X1: Acción situación de calle | Y1: Filial con Antena y Radio Teleco | Z1: Voluntarios con hoja de vida actualizada | AA1: Voluntariado con credencial actualizada | AB1: Filial realiza charlas estatutos y reglamentos? | AC1: Acción cambio climático | AD1: Acciones PGI (protección, género, inclusión) | AE1: Acción CEA (Rendición cuentas a la comunidad) | AF1: Kits alimentos entregados | AG1: Kits higiene entregados | AH1: Kits abrigo entregados | AI1: Voluntarios capacitados en AA | AJ1: Voluntarios capacitados en SPAC | AK1: Voluntarios capacitados en SMAPS | AL1: Voluntarios capacitados en RCF | AM1: Voluntarios capacitados en Manejo Redes | AN1: Voluntarios capacitados en Balances y EERR | AO1: N° personas capacitados en primeros auxilios (comunidad) | AP1: Cantidad Personal rentado | AQ1: Cantidad Unidades Educativas Colegios | AR1: Prioridad Sustentabilidad financiera | AS1: Prioridad Manejo tecnologías | AT1: Prioridad políticas del voluntariado | AU1: Prioridad Liderazgo y estatutos | AV1: Prioridad Derecho internacional y cambio climático | AW1: Preferencia capacitacion | AX1: Relevancia 2024 Gestión del riesgo | AY1: Relevancia 2024 Salud | AZ1: Relevancia 2024 Bienestar Social | BA1: Relevancia 2024 Juventud | BB1: Financiamiento | BC1: Comentario otro financiamiento | BD1: Encuesta confiable? (prioridades y relevancia
B2: Almendral | C2: Valparaíso | D2: 7 | E2: 0 | F2: 70512176-1 | G2: Independencia 2978 | H2: 991413562 | I2: S/I | K2: Sí | L2: No | M2: No | N2: No | O2: No | P2: 0 | Q2: 0 | R2: 0 | S2: 0 | T2: 0 | U2: Sí | V2: No | W2: No | X2: Sí | Y2: No | Z2: Sí | AA2: Sí | AB2: No | AC2: No | AD2: No | AE2: No | AF2: 0 | AG2: 0 | AH2: 160 | AI2: 0 | AJ2: 0 | AK2: 0 | AL2: 0 | AM2: 0 | AN2: 0 | AO2: 0 | AP2: 0 | AQ2: 0 | AR2: 5 | AS2: 4 | AT2: S/I | AU2: S/I | AV2: S/I | AW2: Presencial | AX2: S/I | AY2: 1 | AZ2: 2 | BA2: S/I | BB2: Arriendo | BD2: 0
B3: Angol | C3: Araucanía | D3: 20 | E3: 22 | F3: 70672737-K | G3: Lautaro N° 143 | H3: 96519624 | I3: 44531 | J3: Cr.filialangol | K3: Sí | L3: Sí | M3: No | N3: No | O3: No | P3: 0 | Q3: 0 | R3: 0 | S3: 0 | T3: 1 | U3: No | V3: Sí | W3: No | X3: Sí | Y3: Sí | Z3: Sí | AA3: No | AB3: No | AC3: No | AD3: Sí | AE3: Sí | AF3: 29 | AG3: 29 | AH3: 17 | AI3: 1 | AJ3: 0 | AK3: 0 | AL3: 0 | AM3: 0 | AN3: 0 | AO3: 0 | AP3: 2 | AQ3: 0 | AR3: 4 | AS3: 5 | AT3: 2 | AU3: 1 | AV3: 3 | AW3: Online | AX3: 1 | AY3: 3 | AZ3: 2 | BA3: 4 | BB3: Arriendo | BD3: 1
B4: Antofagasta | C4: Antofagasta | D4: 25 | E4: 5 | F4: 70672705-1 | G4: Calle Adamson 3354 | H4: 722779272 | I4: 44866 | J4: Cruzrojachilena_antofagasta | K4: Sí | L4: Sí | M4: Sí | N4: Sí | O4: Sí | P4: 0 | Q4: 9 | R4: 1 | S4: 1 | T4: 0 | U4: Sí | V4: Sí | W4: Sí | X4: Sí | Y4: Sí | Z4: Sí | AA4: Sí | AB4: No | AC4: No | AD4: Sí | AE4: No | AF4: 70 | AG4: 70 | AH4: 40 | AI4: 0 | AJ4: 0 | AK4: 0 | AL4: 10 | AM4: 1 | AN4: 0 | AO4: 0 | AP4: 0 | AQ4: 0 | AR4: 5 | AS4: 2 | AT4: 1 | AU4: 3 | AV4: 4 | AW4: Presencial | AX4: 3 | AY4: 1 | AZ4: 4 | BA4: 2 | BB4: Cursos PAA | BD4: 1
B5: Arica y Parinacota | C5: Arica Parinacota Tarapacá | D5: 23 | E5: 20 | F5: 70.672.700-0 | G5: San Marcos 356 | H5: 975855192 | I5: 45200 | J5: cruzroja_arica | K5: Sí | L5: Sí | M5: No | N5: Sí | O5: Sí | P5: S/I | Q5: S/I | R5: 1 | S5: 3 | T5: 1 | U5: No | V5: Sí | W5: Sí | X5: Sí | Y5: No | Z5: Sí | AA5: Sí | AB5: Sí | AC5: No | AD5: No | AE5: Sí | AF5: 0 | AG5: 100 | AH5: 20 | AI5: 6 | AJ5: 0 | AK5: 0 | AL5: 6 | AM5: 0 | AN5: 1 | AO5: 0 | AP5: 1 | AQ5: 5 | AR5: 3 | AS5: 2 | AT5: 4 | AU5: 5 | AV5: 1 | AW5: Online | AX5: 1 | AY5: 2 | AZ5: 3 | BA5: 4 | BB5: Subvencíón municipal | BD5: 1
B6: Bulnes | C6: Biobío y Ñuble | D6: 9 | E6: 1 | F6: 70512196-6 | G6: Victor Bianchi N°99 - Comuna Bulnes | H6: 796611917 | I6: 2017 | K6: No | L6: No | M6: Sí | N6: No | O6: Sí | P6: 7 | Q6: 7 | R6: 0 | S6: 0 | T6: 1 | U6: No | V6: No | W6: No | X6: No | Y6: No | Z6: Sí | AA6: Sí | AB6: Sí | AC6: Sí | AD6: Sí | AE6: Sí | AF6: 0 | AG6: 0 | AH6: 0 | AI6: 0 | AJ6: 0 | AK6: 0 | AL6: 0 | AM6: 0 | AN6: 0 | AO6: 0 | AP6: 0 | AQ6: 0 | AR6: 2 | AS6: 4 | AT6: 1 | AU6: 3 | AV6: 5 | AW6: Online | AX6: 2 | AY6: 3 | AZ6: 1 | BA6: 4 | BB6: Subvencíón municipal | BC6: Y aportes voluntarios hogar de ancianos | BD6: 1
B7: Cabrero | C7: Biobío y Ñuble | D7: 12 | E7: 3 | F7: 70672795-7 | G7: Calle Palacios s/n, orilla de carretera, Cabrero. | H7: 999698836 | I7: 45047 | J7: Cruzrojacabrero | K7: Sí | L7: Sí | M7: No | N7: Sí | O7: Sí | P7: 4 | Q7: 2 | R7: 0 | S7: 0 | T7: 2 | U7: Sí | V7: Sí | W7: No | X7: Sí | Y7: No | Z7: No | AA7: No | AB7: No | AC7: No | AD7: Sí | AE7: No | AF7: 56 | AG7: 28 | AH7: 0 | AI7: 1 | AJ7: 0 | AK7: 0 | AL7: 0 | AM7: 0 | AN7: 0 | AO7: 0 | AP7: 0 | AQ7: 0 | AR7: 4 | AS7: 5 | AT7: 2 | AU7: 1 | AV7: 3 | AW7: Online | AX7: 2 | AY7: 1 | AZ7: 3 | BA7: 4 | BB7: Subvencíón municipal | BD7: 1
B8: Caldera | C8: Atacama-Coquimbo | D8: 25 | E8: 5 | F8: 70672708-6 | G8: Gallo 70 | H8: 9320202907 | I8: 44652 | K8: No | L8: No | M8: No | N8: No | O8: Sí | P8: 5 | Q8: 5 | R8: 1 | S8: 1 | T8: 0 | U8: Sí | V8: Sí | W8: No | X8: Sí | Y8: Sí | Z8: Sí | AA8: No | AB8: Sí | AC8: No | AD8: No | AE8: No | AF8: 0 | AG8: 0 | AH8: 0 | AI8: 0 | AJ8: 0 | AK8: 0 | AL8: 0 | AM8: 0 | AN8: 0 | AO8: 0 | AP8: 0 | AQ8: 0 | AR8: S/I | AS8: S/I | AT8: S/I | AU8: S/I | AV8: S/I | AW8: Presencial | AX8: S/I | AY8: 1 | AZ8: 2 | BA8: S/I | BB8: Arriendo | BC8: Y policlínicos, subvención municipal | BD8: 0
B9: Cañete | C9: Biobío y Ñuble | D9: 24 | E9: 8 | F9: 70672735-5 | G9: Arturo Prat N° 437 | H9: 442918911 | I9: 45505 | J9: cruz roja fililal cañete | K9: Sí | L9: Sí | M9: Sí | N9: No | O9: Sí | P9: 3 | Q9: 5 | R9: 2 | S9: 1 | T9: 0 | U9: Sí | V9: No | W9: No | X9: Sí | Y9: No | Z9: Sí | AA9: Sí | AB9: Sí | AC9: Sí | AD9: Sí | AE9: Sí | AF9: 15 | AG9: 47 | AH9: 29 | AI9: 0 | AJ9: 0 | AK9: 0 | AL9: 0 | AM9: 0 | AN9: 0 | AO9: 0 | AP9: 1 | AQ9: 1 | AR9: 5 | AS9: 4 | AT9: 3 | AU9: 2 | AV9: 1 | AW9: Online | AX9: 1 | AY9: 3 | AZ9: 2 | BA9: 4 | BB9: Arriendo | BD9: 0
B10: Capitán Pastene | C10: Araucanía | D10: 20 | E10: 4 | F10: 65191583-K | G10: Garibaldi 708 | H10: 98376158 | I10: 2020 | K10: Sí | L10: No | M10: No | N10: Sí | O10: Sí | P10: 18 | Q10: 18 | R10: 0 | S10: 0 | T10: 0 | U10: Sí | V10: No | W10: No | X10: No | Y10: No | Z10: Sí | AA10: No | AB10: No | AC10: No | AD10: No | AE10: No | AF10: 48 | AG10: 36 | AH10: 96 | AI10: 0 | AJ10: 0 | AK10: 0 | AL10: 0 | AM10: 4 | AN10: 2 | AO10: 2 | AP10: 0 | AQ10: 0 | AR10: 5 | AS10: 4 | AT10: 3 | AU10: 2 | AV10: 1 | AW10: Presencial | AX10: 1 | AY10: 3 | AZ10: 2 | BA10: 4 | BB10: Otro | BC10: Beneficios y arriendo esporádico | BD10: 0
B11: Carahue | C11: Araucanía | D11: 21 | E11: 0 | F11: 70672747-7 | G11: Avenida Ercilla 260 | H11: 997710238 | I11: 43586 | K11: Sí | L11: No | M11: No | N11: No | O11: Sí | P11: 9 | Q11: 14 | R11: 0 | S11: 0 | T11: 0 | U11: Sí | V11: No | W11: No | X11: Sí | Y11: No | Z11: Sí | AA11: No | AB11: Sí | AC11: No | AD11: No | AE11: No | AF11: 30 | AG11: 50 | AH11: 210 | AI11: 0 | AJ11: 0 | AK11: 0 | AL11: 0 | AM11: 0 | AN11: 0 | AO11: 0 | AP11: 0 | AQ11: 0 | AR11: 5 | AS11: 2 | AT11: 4 | AU11: 1 | AV11: 3 | AW11: Mixta | AX11: 2 | AY11: 3 | AZ11: 1 | BA11: 4 | BB11: Arriendo | BD11: 1
B12: Cartagena | C12: Valparaíso | D12: 13 | E12: 0 | F12: 70512189-3 | G12: San Antonio 398 | H12: 979844862 | I12: 45474 | J12: CRUZROJACARTAGENA | K12: Sí | L12: Sí | M12: No | N12: No | O12: Sí | P12: 6 | Q12: 3 | R12: 2 | S12: 0 | T12: 1 | U12: No | V12: Sí | W12: No | X12: Sí | Y12: No | Z12: Sí | AA12: Sí | AB12: Sí | AC12: No | AD12: Sí | AE12: No | AF12: 750 | AG12: 170 | AH12: 300 | AI12: 0 | AJ12: 0 | AK12: 13 | AL12: 0 | AM12: 2 | AN12: 2 | AO12: 9 | AP12: 0 | AQ12: 0 | AR12: 2 | AS12: 1 | AT12: 3 | AU12: 4 | AV12: 5 | AW12: Presencial | AX12: 3 | AY12: 2 | AZ12: 1 | BA12: 4 | BB12: Arriendo | BC12: policlínico, subvención municipal, donaciones | BD12: 1
B13: Castro | C13: Los Lagos y Aysén | D13: 13 | E13: 0 | F13: 70672777-9 | G13: GAmbia 535 Castro | H13: 652633133 | I13: 44197 | K13: No | L13: Sí | M13: No | N13: No | O13: Sí | P13: 2 | Q13: 2 | R13: 0 | S13: 2 | T13: 2 | U13: No | V13: No | W13: Sí | X13: Sí | Y13: Sí | Z13: Sí | AA13: Sí | AB13: No | AC13: No | AD13: Sí | AE13: No | AF13: 105 | AG13: 105 | AH13: 120 | AI13: 0 | AJ13: 0 | AK13: 0 | AL13: 0 | AM13: 0 | AN13: 0 | AO13: 0 | AP13: 0 | AQ13: 0 | AR13: 5 | AS13: 3 | AT13: 1 | AU13: 2 | AV13: 4 | AW13: Presencial | AX13: 2 | AY13: 3 | AZ13: 1 | BA13: 4 | BB13: Arriendo | BC13: aporte de voluntariados, beneficios, socios colaboradores, campaña del sobre | BD13: 1
B14: Cauquenes | C14: Maule | D14: 22 | E14: 0 | F14: 65015007-4 | G14: Antonio Varas 1019 | H14: 976570039 | I14: S/I | K14: Sí | L14: Sí | M14: No | N14: Sí | O14: Sí | P14: 20 | Q14: 8 | R14: 3 | S14: 0 | T14: 0 | U14: No | V14: No | W14: No | X14: No | Y14: Sí | Z14: Sí | AA14: No | AB14: Sí | AC14: No | AD14: No | AE14: No | AF14: 120 | AG14: 43 | AH14: 45 | AI14: 4 | AJ14: 0 | AK14: 0 | AL14: 0 | AM14: 3 | AN14: 0 | AO14: 0 | AP14: 0 | AQ14: 0 | AR14: 5 | AS14: 4 | AT14: 2 | AU14: 1 | AV14: 3 | AW14: Presencial | AX14: 1 | AY14: 2 | AZ14: 3 | BA14: 4 | BB14: Arriendo | BD14: 1
B15: Chiguayante | C15: Biobío y Ñuble | D15: 47 | E15: 6 | F15: 70672722-1 | G15: Prat 80 | H15: 979388879 | I15: 44531 | J15: crz_roja_juventud_chiguayante | K15: Sí | L15: Sí | M15: Sí | N15: No | O15: Sí | P15: 6 | Q15: 6 | R15: 0 | S15: 4 | T15: 1 | U15: Sí | V15: Sí | W15: Sí | X15: Sí | Y15: No | Z15: Sí | AA15: Sí | AB15: Sí | AC15: No | AD15: Sí | AE15: Sí | AF15: 230 | AG15: 82 | AH15: 60 | AI15: 0 | AJ15: 0 | AK15: 0 | AL15: 0 | AM15: 0 | AN15: 0 | AO15: 2 | AP15: 0 | AQ15: 0 | AR15: 1 | AS15: 2 | AT15: 3 | AU15: 4 | AV15: 5 | AW15: Presencial | AX15: 3 | AY15: 2 | AZ15: 1 | BA15: 4 | BB15: Subvencíón municipal | BD15: 0
B16: Chillán | C16: Biobío y Ñuble | D16: 33 | E16: 9 | F16: 70512195-8 | G16: Maipón 301 Chillán | H16: 993204220 | I16: 43678 | J16: cruzrojachilena.chillan | K16: Sí | L16: Sí | M16: Sí | N16: Sí | O16: Sí | P16: 4 | Q16: 8 | R16: 0 | S16: 4 | T16: 3 | U16: Sí | V16: No | W16: No | X16: Sí | Y16: Sí | Z16: Sí | AA16: Sí | AB16: No | AC16: Sí | AD16: Sí | AE16: Sí | AF16: 15 | AG16: 213 | AH16: 219 | AI16: 2 | AJ16: 4 | AK16: 0 | AL16: 1 | AM16: 0 | AN16: 0 | AO16: 146 | AP16: 0 | AQ16: 5 | AR16: 2 | AS16: 5 | AT16: 1 | AU16: 3 | AV16: 4 | AW16: Presencial | AX16: 1 | AY16: 2 | AZ16: 3 | BA16: 4 | BB16: Cursos PAA | BC16: Subvención municipal de proyectos específicos | BD16: 1
B17: Coelemu | C17: Biobío y Ñuble | D17: 9 | E17: 2 | F17: 70512197-4 | G17: Palazuelos 265 | H17: 923710907 | I17: 2016 | J17: Cruzrojacoelemu | K17: Sí | L17: Sí | M17: No | N17: Sí | O17: Sí | P17: 2 | Q17: 2 | R17: 2 | S17: 1 | T17: 1 | U17: No | V17: No | W17: No | X17: No | Y17: Sí | Z17: Sí | AA17: Sí | AB17: Sí | AC17: Sí | AD17: Sí | AE17: No | AF17: 73 | AG17: 35 | AH17: 0 | AI17: 1 | AJ17: 2 | AK17: 0 | AL17: 1 | AM17: 1 | AN17: 3 | AO17: 57 | AP17: 0 | AQ17: 0 | AR17: 2 | AS17: 5 | AT17: 4 | AU17: 1 | AV17: 3 | AW17: Mixta | AX17: 1 | AY17: 3 | AZ17: 2 | BA17: 4 | BB17: Arriendo | BD17: 1
B18: Collipulli | C18: Araucanía | D18: 24 | E18: 4 | F18: 70672738-8 | G18: Calle Cruz N16 | H18: 987504663 | I18: 45444 | J18: cr.filialcollipulli | K18: Sí | L18: Sí | M18: No | N18: No | O18: Sí | P18: 8 | Q18: 8 | R18: 1 | S18: 0 | T18: 0 | U18: No | V18: No | W18: Sí | X18: Sí | Y18: No | Z18: Sí | AA18: No | AB18: No | AC18: No | AD18: No | AE18: No | AF18: 8 | AG18: 10 | AH18: 20 | AI18: 0 | AJ18: 0 | AK18: 0 | AL18: 0 | AM18: 0 | AN18: 0 | AO18: 0 | AP18: 0 | AQ18: 0 | AR18: 3 | AS18: 5 | AT18: 1 | AU18: 2 | AV18: 4 | AW18: Online | AX18: 2 | AY18: 4 | AZ18: 1 | BA18: 3 | BB18: Otro | BC18: Donaciones | BD18: 1
B19: Concepción | C19: Biobío y Ñuble | D19: 76 | E19: 2 | F19: 70672724-8 | G19: Lautaro 509 | H19: 412954653 | I19: 45566 | J19: Cruz.roja.concepcion | K19: Sí | L19: Sí | M19: Sí | N19: Sí | O19: Sí | P19: 10 | Q19: 11 | R19: 3 | S19: 4 | T19: 1 | U19: No | V19: No | W19: No | X19: Sí | Y19: Sí | Z19: Sí | AA19: Sí | AB19: Sí | AC19: No | AD19: No | AE19: No | AF19: 93 | AG19: 34 | AH19: 27 | AI19: 3 | AJ19: 1 | AK19: 0 | AL19: 2 | AM19: 1 | AN19: 0 | AO19: 137 | AP19: 0 | AQ19: 2 | AR19: 5 | AS19: 2 | AT19: 1 | AU19: 3 | AV19: 4 | AW19: Presencial | AX19: 1 | AY19: 2 | AZ19: 4 | BA19: 3 | BB19: Cursos PAA | BD19: 1
B20: Concón | C20: Valparaíso | D20: 14 | E20: 8 | F20: S/I | G20: Av. Reñaca Concón con los Alerces | H20: 985768450 | I20: S/I | J20: CRUZ ROJA CONCON | K20: Sí | L20: Sí | M20: Sí | N20: No | O20: Sí | P20: 6 | Q20: 6 | R20: 0 | S20: 1 | T20: 0 | U20: Sí | V20: Sí | W20: Sí | X20: No | Y20: Sí | Z20: Sí | AA20: Sí | AB20: No | AC20: Sí | AD20: Sí | AE20: Sí | AF20: 0 | AG20: 0 | AH20: 0 | AI20: 0 | AJ20: 0 | AK20: 0 | AL20: 0 | AM20: 0 | AN20: 0 | AO20: 0 | AP20: 0 | AQ20: 0 | AR20: 1 | AS20: 2 | AT20: 5 | AU20: 4 | AV20: 3 | AW20: Online | AX20: 2 | AY20: 1 | AZ20: 4 | BA20: 3 | BB20: Subvencíón municipal | BD20: 0
B21: Copiapó | C21: Atacama-Coquimbo | D21: 20 | E21: 6 | F21: 70672709-4 | G21: Chañarcillo n°300 | H21: 981820329 | I21: 44652 | K21: No | L21: Sí | M21: Sí | N21: Sí | O21: Sí | P21: 2 | Q21: 8 | R21: 7 | S21: 1 | T21: 2 | U21: No | V21: No | W21: Sí | X21: Sí | Y21: Sí | Z21: Sí | AA21: No | AB21: Sí | AC21: No | AD21: Sí | AE21: Sí | AF21: 100 | AG21: 30 | AH21: 10 | AI21: 0 | AJ21: 2 | AK21: 0 | AL21: 2 | AM21: 2 | AN21: 1 | AO21: 0 | AP21: 0 | AQ21: 0 | AR21: 1 | AS21: 5 | AT21: 4 | AU21: 2 | AV21: 3 | AW21: Online | AX21: 4 | AY21: 1 | AZ21: 2 | BA21: 3 | BB21: Otro | BC21: Aporte voluntarios, aportes de rifa beneficio filial | BD21: 1
B22: Coquimbo | C22: Atacama-Coquimbo | D22: 17 | E22: 10 | F22: 70672713-2 | G22: Melgarejo 1035 | H22: 51 2311166 | I22: S/I | J22: @filialcoquimbo | K22: Sí | L22: Sí | M22: Sí | N22: No | O22: Sí | P22: S/I | Q22: S/I | R22: 0 | S22: 0 | T22: 0 | U22: No | V22: Sí | W22: Sí | X22: Sí | Y22: Sí | Z22: No | AA22: No | AB22: No | AC22: No | AD22: Sí | AE22: No | AF22: 0 | AG22: 0 | AH22: 0 | AI22: 0 | AJ22: 3 | AK22: 0 | AL22: 6 | AM22: 2 | AN22: 0 | AO22: 0 | AP22: 4 | AQ22: 0 | AR22: 3 | AS22: 5 | AT22: 2 | AU22: 1 | AV22: 4 | AW22: Mixta | AX22: 3 | AY22: 2 | AZ22: 1 | BA22: 4 | BB22: Policlínico | BD22: 1
B23: Cordillera | C23: Valparaíso | D23: 23 | E23: 0 | F23: 70512163-K | G23: Cahaparro 90 Cerro Cordillera Valparaíso | H23: 945802224 | I23: 45474 | J23: filial.cordillera | K23: Sí | L23: Sí | M23: No | N23: No | O23: Sí | P23: 8 | Q23: 1 | R23: 3 | S23: 1 | T23: 0 | U23: Sí | V23: No | W23: Sí | X23: Sí | Y23: No | Z23: Sí | AA23: Sí | AB23: Sí | AC23: Sí | AD23: Sí | AE23: Sí | AF23: 50 | AG23: 30 | AH23: 50 | AI23: 1 | AJ23: 0 | AK23: 2 | AL23: 2 | AM23: 1 | AN23: 0 | AO23: 0 | AP23: 0 | AQ23: 0 | AR23: 3 | AS23: 2 | AT23: 4 | AU23: 1 | AV23: 5 | AW23: Presencial | AX23: 3 | AY23: 2 | AZ23: 1 | BA23: 4 | BB23: Otro | BC23: Donaciones y Beneficios | BD23: 1
B24: Coyhaique | C24: Los Lagos y Aysén | D24: 10 | E24: 0 | F24: 70672779-5 | G24: Las Quintas 808 | H24: 56977997 | I24: S/I | J24: CRUZROJACHILENA_COYHAIQUE | K24: Sí | L24: Sí | M24: No | N24: No | O24: Sí | P24: 5 | Q24: 5 | R24: 0 | S24: 0 | T24: 0 | U24: No | V24: No | W24: Sí | X24: Sí | Y24: Sí | Z24: Sí | AA24: Sí | AB24: No | AC24: No | AD24: No | AE24: No | AF24: 30 | AG24: 0 | AH24: 20 | AI24: 0 | AJ24: 0 | AK24: 0 | AL24: 0 | AM24: 0 | AN24: 0 | AO24: 0 | AP24: 0 | AQ24: 0 | AR24: 3 | AS24: 4 | AT24: 1 | AU24: 2 | AV24: 5 | AW24: Presencial | AX24: 3 | AY24: 2 | AZ24: 1 | BA24: 4 | BB24: Otro | BC24: Beneficio venta de empanadas | BD24: 0
B25: Curanilahue | C25: Biobío y Ñuble | D25: 11 | E25: 9 | F25: 70512192-3 | G25: Calle nueva S/N, Curanilahue | H25: 962051572 | I25: 44409 | K25: No | L25: No | M25: No | N25: Sí | O25: Sí | P25: 10 | Q25: 11 | R25: 0 | S25: 0 | T25: 0 | U25: No | V25: No | W25: No | X25: Sí | Y25: No | Z25: Sí | AA25: No | AB25: No | AC25: No | AD25: Sí | AE25: Sí | AF25: 92 | AG25: 105 | AH25: 0 | AI25: 0 | AJ25: 0 | AK25: 0 | AL25: 0 | AM25: 11 | AN25: 2 | AO25: 10 | AP25: 0 | AQ25: 0 | AR25: 1 | AS25: 3 | AT25: 4 | AU25: 5 | AV25: 2 | AW25: Presencial | AX25: 4 | AY25: 3 | AZ25: 2 | BA25: 1 | BB25: Subvencíón municipal | BD25: 0
B26: Curicó | C26: Maule | D26: 31 | E26: 13 | F26: 70512145-1 | G26: Estado 206 Curicó | H26: 927615972 | I26: 44927 | J26: cruzrojacurico | K26: Sí | L26: Sí | M26: Sí | N26: Sí | O26: Sí | P26: 2 | Q26: 1 | R26: 0 | S26: 1 | T26: 1 | U26: No | V26: No | W26: Sí | X26: Sí | Y26: No | Z26: Sí | AA26: No | AB26: No | AC26: No | AD26: Sí | AE26: Sí | AF26: 20 | AG26: 30 | AH26: 40 | AI26: 4 | AJ26: 2 | AK26: 1 | AL26: 0 | AM26: 0 | AN26: 0 | AO26: 60 | AP26: 1 | AQ26: 0 | AR26: 1 | AS26: 3 | AT26: 4 | AU26: 5 | AV26: 2 | AW26: Presencial | AX26: 3 | AY26: 2 | AZ26: 4 | BA26: 1 | BB26: Arriendo | BD26: 1
B27: El Loa | C27: Antofagasta | D27: 58 | E27: 10 | F27: 70672703-5 | G27: Balmaceda 1932 Calama | H27: 973650711 | I27: 45413 | J27: instagram | K27: Sí | L27: Sí | M27: No | N27: No | O27: Sí | P27: 5 | Q27: 25 | R27: 1 | S27: 0 | T27: 3 | U27: No | V27: Sí | W27: Sí | X27: Sí | Y27: Sí | Z27: Sí | AA27: No | AB27: Sí | AC27: Sí | AD27: Sí | AE27: No | AF27: 150 | AG27: 150 | AH27: 150 | AI27: 0 | AJ27: 0 | AK27: 0 | AL27: 2 | AM27: 1 | AN27: 1 | AO27: 60 | AP27: 0 | AQ27: 2 | AR27: 5 | AS27: 3 | AT27: 1 | AU27: 2 | AV27: 4 | AW27: Presencial | AX27: 3 | AY27: 4 | AZ27: 1 | BA27: 2 | BB27: Arriendo | BC27: Subvención Municipal | BD27: 1
B28: El Monte | C28: Metropolitana | D28: 11 | E28: 3 | F28: 70512117-6 | G28: Ignacio Carrera Pinto 044 | H28: 982383360 | I28: 2001 | J28: Cruz_roja_filial_el_monte | K28: Sí | L28: Sí | M28: No | N28: No | O28: Sí | P28: 6 | Q28: 6 | R28: 0 | S28: 0 | T28: 0 | U28: No | V28: No | W28: Sí | X28: Sí | Y28: Sí | Z28: Sí | AA28: No | AB28: No | AC28: No | AD28: Sí | AE28: No | AF28: 0 | AG28: 20 | AH28: 20 | AI28: 0 | AJ28: 0 | AK28: 0 | AL28: 0 | AM28: 0 | AN28: 1 | AO28: 0 | AP28: 0 | AQ28: 0 | AR28: 5 | AS28: 4 | AT28: 1 | AU28: 2 | AV28: 3 | AW28: Presencial | AX28: 3 | AY28: 1 | AZ28: 2 | BA28: 4 | BB28: Otro | BC28: atención podológica | BD28: 1
B29: El Quisco | C29: Valparaíso | D29: 10 | E29: 0 | F29: 70512163-K | G29: Alcalde Raul Romero Erazo 0375 | H29: 995985661 | I29: S/I | J29: cruzrojaelquisco | K29: Sí | L29: Sí | M29: Sí | N29: Sí | O29: Sí | P29: 4 | Q29: 4 | R29: 0 | S29: 1 | T29: 1 | U29: Sí | V29: No | W29: Sí | X29: Sí | Y29: Sí | Z29: Sí | AA29: Sí | AB29: No | AC29: No | AD29: No | AE29: No | AF29: 300 | AG29: 250 | AH29: 150 | AI29: 0 | AJ29: 0 | AK29: 0 | AL29: 0 | AM29: 0 | AN29: 0 | AO29: 0 | AP29: 0 | AQ29: 0 | AR29: 1 | AS29: 2 | AT29: 3 | AU29: 5 | AV29: 4 | AW29: Mixta | AX29: 1 | AY29: S/I | AZ29: 2 | BA29: S/I | BB29: Cursos PAA | BC29: y subvención municipal | BD29: 0
B30: Frutillar | C30: Los Lagos y Aysén | D30: 13 | E30: 3 | F30: 70672769-2 | G30: Anibal Pinto 153 | H30: 950169720 | I30: 44501 | K30: No | L30: No | M30: Sí | N30: Sí | O30: Sí | P30: 3 | Q30: 3 | R30: 0 | S30: 0 | T30: 0 | U30: Sí | V30: No | W30: Sí | X30: No | Y30: No | Z30: Sí | AA30: Sí | AB30: Sí | AC30: No | AD30: No | AE30: No | AF30: 0 | AG30: 0 | AH30: 0 | AI30: 0 | AJ30: 0 | AK30: 0 | AL30: 0 | AM30: 0 | AN30: 0 | AO30: 0 | AP30: 0 | AQ30: 0 | AR30: 4 | AS30: 3 | AT30: 1 | AU30: 2 | AV30: 5 | AW30: Online | AX30: S/I | AY30: S/I | AZ30: S/I | BA30: S/I | BB30: Arriendo | BD30: 0
B31: Gorbea | C31: Araucanía | D31: 21 | E31: 0 | F31: 70672750-7 | G31: Cochrane N° 401 Gorbea | H31: 978736669 | I31: S/I | J31: Cruz_Roja_gorbea | K31: Sí | L31: Sí | M31: Sí | N31: No | O31: Sí | P31: 21 | Q31: 21 | R31: 0 | S31: 0 | T31: 0 | U31: No | V31: No | W31: No | X31: Sí | Y31: No | Z31: Sí | AA31: Sí | AB31: No | AC31: No | AD31: No | AE31: Sí | AF31: 0 | AG31: 0 | AH31: 0 | AI31: 2 | AJ31: 0 | AK31: 0 | AL31: 0 | AM31: 7 | AN31: 2 | AO31: 0 | AP31: 1 | AQ31: 0 | AR31: 5 | AS31: 4 | AT31: 3 | AU31: 2 | AV31: 1 | AW31: Presencial | AX31: 4 | AY31: 2 | AZ31: 1 | BA31: 4 | BB31: Subvencíón municipal | BC31: y comedor social | BD31: 0
B32: Illapel | C32: Atacama-Coquimbo | D32: 12 | E32: 2 | F32: 70672715-9 | G32: Ramón Freire # 350 | H32: 532523101 | I32: en proceso | K32: No | L32: No | M32: No | N32: No | O32: Sí | P32: S/I | Q32: S/I | R32: 0 | S32: 0 | T32: 0 | U32: Sí | V32: No | W32: No | X32: Sí | Y32: No | Z32: Sí | AA32: No | AB32: No | AC32: No | AD32: Sí | AE32: Sí | AF32: 87 | AG32: 48 | AH32: 15 | AI32: 0 | AJ32: 0 | AK32: 0 | AL32: 0 | AM32: 0 | AN32: 0 | AO32: 0 | AP32: 1 | AQ32: 0 | AR32: 1 | AS32: 2 | AT32: 3 | AU32: 4 | AV32: 5 | AW32: Online | AX32: S/I | AY32: S/I | AZ32: 1 | BA32: S/I | BB32: Arriendo | BC32: Y box dental | BD32: 0
B33: Iquique | C33: Arica Parinacota Tarapacá | D33: 24 | E33: 20 | F33: 70.672.701-9 | G33: Obispo Labbé #800 | H33: 572344939 | I33: S/I | J33: cruzroja.filial.iquique | K33: Sí | L33: Sí | M33: Sí | N33: Sí | O33: Sí | P33: 5 | Q33: 15 | R33: 1 | S33: 3 | T33: 1 | U33: Sí | V33: Sí | W33: Sí | X33: Sí | Y33: No | Z33: Sí | AA33: Sí | AB33: No | AC33: No | AD33: Sí | AE33: Sí | AF33: 1500 | AG33: 1500 | AH33: 1500 | AI33: 1 | AJ33: 1 | AK33: 30 | AL33: 9 | AM33: 0 | AN33: 1 | AO33: 500 | AP33: 0 | AQ33: 0 | AR33: 5 | AS33: 4 | AT33: 3 | AU33: 2 | AV33: 1 | AW33: Mixta | AX33: 1 | AY33: 2 | AZ33: 3 | BA33: 4 | BB33: Cursos PAA | BC33: y policlínicos | BD33: 0
B34: La Cisterna | C34: Metropolitana | D34: 11 | E34: 1 | F34: 70512119-2 | G34: Pablo Goyeneche 17 | H34: 986284017 | I34: 45566 | J34: Lacisterna.oficial | K34: Sí | L34: Sí | M34: No | N34: No | O34: Sí | P34: 4 | Q34: 5 | R34: 1 | S34: 1 | T34: 0 | U34: No | V34: No | W34: Sí | X34: Sí | Y34: No | Z34: Sí | AA34: Sí | AB34: No | AC34: No | AD34: Sí | AE34: No | AF34: 35 | AG34: 325 | AH34: 0 | AI34: 0 | AJ34: 0 | AK34: 0 | AL34: 1 | AM34: 0 | AN34: 1 | AO34: 49 | AP34: 0 | AQ34: 0 | AR34: 5 | AS34: 4 | AT34: 1 | AU34: 2 | AV34: 3 | AW34: Online | AX34: 1 | AY34: 3 | AZ34: 2 | BA34: 4 | BB34: Cursos PAA | BC34: y subvención municipal | BD34: 0
B35: La Serena | C35: Atacama-Coquimbo | F35: 70672711-6 | G35: Cienfuegos 470 | H35: 967252337 | I35: 44774 | K35: Sí | L35: No | M35: No | N35: Sí | O35: No | P35: 0 | Q35: 0 | R35: 0 | S35: 2 | T35: 0 | U35: Sí | V35: No | W35: Sí | X35: Sí | Y35: Sí | Z35: Sí | AA35: Sí | AB35: No | AC35: No | AD35: Sí | AE35: No | AF35: 0 | AG35: 0 | AH35: 0 | AI35: 0 | AJ35: 0 | AK35: 0 | AL35: 0 | AM35: 0 | AN35: 0 | AO35: 12 | AP35: 3 | AQ35: 0 | AR35: 1 | AS35: 2 | AT35: 3 | AU35: 4 | AV35: 5 | AW35: Presencial | AX35: 1 | AY35: 2 | AZ35: 4 | BA35: 3 | BB35: Policlínico | BC35: Y arriendos | BD35: 1
B36: La Unión | C36: Los Ríos | F36: 70672760-4 | G36: Barros Arana 569 | H36: 642322528 | I36: 44562 | J36: CRUZ ROJA-LU | K36: Sí | L36: Sí | M36: Sí | N36: Sí | O36: Sí | P36: 4 | Q36: 4 | R36: 0 | S36: 0 | T36: 0 | U36: No | V36: No | W36: Sí | X36: Sí | Y36: No | Z36: Sí | AA36: Sí | AB36: Sí | AC36: No | AD36: No | AE36: Sí | AF36: 283 | AG36: 3504 | AH36: 0 | AI36: 0 | AJ36: 0 | AK36: 0 | AL36: 0 | AM36: 0 | AN36: 0 | AO36: 0 | AP36: 1 | AQ36: 0 | AR36: 3 | AS36: 2 | AT36: 1 | AU36: 4 | AV36: 5 | AW36: Presencial | AX36: S/I | AY36: 1 | AZ36: 2 | BA36: S/I | BD36: 1
B37: Lago Ranco | C37: Los Ríos | F37: 70672763-9 | G37: Calle Valparaíso SN | H37: 944903828 | I37: S/I | K37: Sí | L37: Sí | M37: No | N37: Sí | O37: No | P37: 0 | Q37: 0 | R37: 0 | S37: 0 | T37: 0 | U37: Sí | V37: No | W37: No | X37: No | Y37: Sí | Z37: Sí | AA37: Sí | AB37: Sí | AC37: No | AD37: No | AE37: No | AF37: 20 | AG37: 99 | AH37: 0 | AI37: 0 | AJ37: 0 | AK37: 0 | AL37: 0 | AM37: 0 | AN37: 0 | AO37: 0 | AP37: 0 | AQ37: 0 | AR37: 2 | AS37: 1 | AT37: 3 | AU37: 4 | AV37: 5 | AW37: Presencial | AX37: 3 | AY37: 2 | AZ37: 1 | BA37: 4 | BD37: 1
B38: Lanco | C38: Los Ríos | F38: 70672755-8 | G38: Calle Valparaíso Recinto casas tuteladas | H38: - | I38: S/I | K38: Sí | L38: Sí | M38: Sí | N38: No | O38: Sí | P38: 0 | Q38: 9 | R38: 0 | S38: 0 | T38: 0 | U38: No | V38: No | W38: No | X38: Sí | Y38: No | Z38: No | AA38: Sí | AB38: No | AC38: No | AD38: Sí | AE38: No | AF38: 0 | AG38: 0 | AH38: 0 | AI38: 0 | AJ38: 0 | AK38: 0 | AL38: 0 | AM38: 0 | AN38: 0 | AO38: 0 | AP38: 0 | AQ38: 0 | AR38: 2 | AS38: 1 | AT38: 3 | AU38: 4 | AV38: 5 | AW38: Presencial | AX38: 3 | AY38: 2 | AZ38: 1 | BA38: 4 | BB38: Subvencíón municipal | BD38: 1
B39: Lastarria | C39: Araucanía | F39: 75327500-2 | G39: 18 de sept 489, lastarria | H39: 989151454 | I39: 45413 | K39: Sí | L39: Sí | M39: No | N39: No | O39: Sí | P39: 4 | Q39: 5 | R39: 0 | S39: 0 | T39: 0 | U39: No | V39: No | W39: No | X39: No | Y39: No | Z39: Sí | AA39: No | AB39: Sí | AC39: No | AD39: No | AE39: Sí | AF39: 70 | AG39: 15 | AH39: 0 | AI39: 0 | AJ39: 0 | AK39: 0 | AL39: 0 | AM39: 0 | AN39: 0 | AO39: 0 | AP39: 0 | AQ39: 0 | AR39: 2 | AS39: 3 | AT39: 1 | AU39: 4 | AV39: 5 | AW39: Presencial | AX39: 1 | AY39: 3 | AZ39: 4 | BA39: 2 | BB39: Otro | BC39: Coronas de caridad | BD39: 0
B40: Lebu | C40: Biobío y Ñuble | F40: 70672734-5 | G40: Saavedra 539 Lebu | H40: 998656463 | I40: 45261 | K40: No | L40: Sí | M40: Sí | N40: Sí | O40: Sí | P40: 0 | Q40: 1 | R40: 0 | S40: 4 | T40: 0 | U40: No | V40: No | W40: Sí | X40: Sí | Y40: Sí | Z40: Sí | AA40: Sí | AB40: Sí | AC40: Sí | AD40: Sí | AE40: Sí | AF40: 35 | AG40: 36 | AH40: 19 | AI40: 2 | AJ40: 0 | AK40: 0 | AL40: 1 | AM40: 1 | AN40: 1 | AO40: 74 | AP40: 0 | AQ40: 0 | AR40: 1 | AS40: 2 | AT40: 4 | AU40: 3 | AV40: 5 | AW40: Presencial | AX40: 3 | AY40: 2 | AZ40: 1 | BA40: 4 | BB40: Arriendo | BD40: 1
B41: Lican Ray | C41: Araucanía | F41: 70672785 -K | G41: GENERAL URRUTIA 835 | H41: 982306102 | I41: 44835 | J41: Cruzroja_licanray | K41: Sí | L41: Sí | M41: No | N41: No | O41: Sí | P41: 18 | Q41: 16 | R41: 0 | S41: 0 | T41: 0 | U41: No | V41: No | W41: No | X41: No | Y41: Sí | Z41: Sí | AA41: No | AB41: Sí | AC41: Sí | AD41: No | AE41: No | AF41: 20 | AG41: 120 | AH41: 10 | AI41: 0 | AJ41: 0 | AK41: 0 | AL41: 0 | AM41: 1 | AN41: 0 | AO41: 0 | AP41: 0 | AQ41: 0 | AR41: 4 | AS41: 2 | AT41: 5 | AU41: 1 | AV41: 3 | AW41: Presencial | AX41: 2 | AY41: 4 | AZ41: 1 | BA41: 3 | BB41: Arriendo | BC41: y subvención municipal | BD41: 1
B42: Limache | C42: Valparaíso | F42: 70512173-7 | G42: Serrano 341 | H42: 958250550 | I42: 45108 | J42: @Cruzrojafiliallimache | K42: Sí | L42: Sí | M42: Sí | N42: Sí | O42: Sí | P42: 15 | Q42: 14 | R42: 0 | S42: 0 | T42: 0 | U42: Sí | V42: No | W42: Sí | X42: Sí | Y42: Sí | Z42: Sí | AA42: Sí | AB42: Sí | AC42: Sí | AD42: Sí | AE42: No | AF42: 210 | AG42: 278 | AH42: 320 | AI42: 0 | AJ42: 0 | AK42: 2 | AL42: 0 | AM42: 2 | AN42: 0 | AO42: 0 | AP42: 0 | AQ42: 0 | AR42: 1 | AS42: 4 | AT42: 5 | AU42: 2 | AV42: 3 | AW42: Mixta | AX42: 2 | AY42: 1 | AZ42: 3 | BA42: 4 | BB42: Subvencíón municipal | BD42: 1
B43: Llanquihue | C43: Los Lagos y Aysén | F43: 70672771-k | G43: Avenida Matta SN | H43: 949435335 | I43: 44440 | J43: cruzrojallanquihue | K43: Sí | L43: Sí | M43: No | N43: Sí | O43: Sí | P43: 1 | Q43: 2 | R43: 0 | S43: 4 | T43: 1 | U43: Sí | V43: Sí | W43: Sí | X43: Sí | Y43: No | Z43: Sí | AA43: Sí | AB43: No | AC43: No | AD43: Sí | AE43: No | AF43: 33 | AG43: 0 | AH43: 9 | AI43: 1 | AJ43: 0 | AK43: 0 | AL43: 2 | AM43: 1 | AN43: 1 | AO43: 12 | AP43: 0 | AQ43: 0 | AR43: 4 | AS43: 2 | AT43: 3 | AU43: 1 | AV43: 5 | AW43: Mixta | AX43: 3 | AY43: 2 | AZ43: 1 | BA43: 4 | BB43: Subvencíón municipal | BD43: 1
B44: Llolleo | C44: Valparaíso | F44: 70512191-5 | G44: Echaurren 242 | H44: - | I44: S/I | J44: filial.llolleo@cruzroja.cl | K44: Sí | L44: Sí | M44: Sí | N44: No | O44: Sí | P44: 0 | Q44: S/I | R44: 0 | S44: 0 | T44: 0 | U44: Sí | V44: No | W44: No | X44: Sí | Y44: No | Z44: Sí | AA44: No | AB44: Sí | AC44: No | AD44: Sí | AE44: No | AF44: 30 | AG44: 30 | AH44: 30 | AI44: 0 | AJ44: 0 | AK44: 0 | AL44: 0 | AM44: 0 | AN44: 0 | AO44: 0 | AP44: 0 | AQ44: 0 | AR44: 5 | AS44: 1 | AT44: 4 | AU44: 2 | AV44: 3 | AW44: Presencial | AX44: 3 | AY44: 2 | AZ44: 1 | BA44: 4 | BB44: Arriendo | BC44: Y Cuotas de Voluntarias | BD44: 1
B45: Lo Espejo | C45: Metropolitana | F45: 70512120-6 | G45: Astaburuaga 87 | H45: 4430445651 | I45: 44835 | K45: No | L45: No | M45: Sí | N45: Sí | S45: si | BD45: 0
B46: Lo Miranda | C46: Bernardo O'Higgins | F46: 70512128-1 | G46: Pedro Aguirre Cerda 069 | H46: 974318583 | I46: 44835 | K46: Sí | L46: Sí | M46: Sí | N46: No | O46: No | P46: 0 | Q46: 0 | R46: 0 | S46: 0 | T46: 0 | U46: No | V46: No | W46: No | X46: No | Y46: Sí | Z46: Sí | AA46: No | AB46: Sí | AC46: No | AD46: Sí | AE46: No | AF46: 24 | AG46: 24 | AH46: 0 | AI46: 0 | AJ46: 0 | AK46: 0 | AL46: 0 | AM46: 1 | AN46: 0 | AO46: 0 | AP46: 0 | AQ46: 0 | AR46: 5 | AS46: 4 | AT46: 3 | AU46: 2 | AV46: 1 | AW46: Online | AX46: 1 | AY46: 2 | AZ46: 3 | BA46: 4 | BB46: Subvencíón municipal | BD46: 0
B47: Loncoche | C47: Araucanía | F47: 70672752-3 | G47: Martínez de Rosas 317 | H47: 987969235 | I47: 45597 | J47: CRUZ ROJA CHILENA FILIAL LONCOCHE | K47: Sí | L47: No | M47: Sí | N47: No | O47: Sí | P47: S/I | Q47: S/I | R47: 0 | S47: 0 | T47: 0 | U47: No | V47: No | W47: No | X47: No | Y47: Sí | Z47: Sí | AA47: No | AB47: No | AC47: No | AD47: Sí | AE47: No | AF47: 5 | AG47: 5 | AH47: 3 | AI47: 0 | AJ47: 0 | AK47: 0 | AL47: 0 | AM47: 0 | AN47: 1 | AO47: 0 | AP47: 0 | AQ47: 0 | AR47: 1 | AS47: 2 | AT47: 3 | AU47: 4 | AV47: 5 | AW47: Mixta | AX47: 4 | AY47: 1 | AZ47: 2 | BA47: 3 | BB47: Arriendo | BD47: 0
B48: Los Andes | C48: Valparaíso | F48: 70512169-9 | G48: Membrillar 98 | H48: 995697671 | I48: 45474 | J48: Cruzrojalosandes22 | K48: Sí | L48: Sí | M48: No | N48: Sí | O48: Sí | P48: 2 | Q48: 1 | R48: 0 | S48: 0 | T48: 1 | U48: Sí | V48: Sí | W48: No | X48: Sí | Y48: Sí | Z48: No | AA48: No | AB48: No | AC48: No | AD48: Sí | AE48: No | AF48: 20 | AG48: 15 | AH48: 0 | AI48: 0 | AJ48: 3 | AK48: 16 | AL48: 1 | AM48: 2 | AN48: 0 | AO48: 2 | AP48: 0 | AQ48: 2 | AR48: 1 | AS48: 2 | AT48: 5 | AU48: 3 | AV48: 4 | AW48: Presencial | AX48: 3 | AY48: 1 | AZ48: 2 | BA48: 4 | BB48: Otro | BC48: cuota de voluntariado | BD48: 0
B49: Los Ángeles | C49: Biobío y Ñuble | F49: 70672730-2 | G49: San Martín 301 | H49: 88510194 | I49: 2017 | J49: cruz-roja-losangeles | K49: Sí | L49: Sí | M49: No | N49: No | O49: Sí | P49: 2 | Q49: 1 | R49: 1 | S49: 2 | T49: 0 | U49: No | V49: Sí | W49: Sí | X49: Sí | Y49: Sí | Z49: Sí | AA49: Sí | AB49: No | AC49: No | AD49: Sí | AE49: Sí | AF49: 15 | AG49: 20 | AH49: 10 | AI49: 1 | AJ49: 1 | AK49: 0 | AL49: 1 | AM49: 1 | AN49: 2 | AO49: 0 | AP49: 0 | AQ49: 0 | AR49: 1 | AS49: 2 | AT49: 3 | AU49: 4 | AV49: 5 | AW49: Online | AX49: 1 | AY49: 2 | AZ49: 3 | BA49: 4 | BB49: Policlínico | BD49: 0
B50: Los Placeres | C50: Valparaíso | F50: 70512182-6 | G50: Amalia Paz 581 cerro Los Placeres | H50: S/I | I50: 45444 | K50: No | L50: No | M50: No | N50: No | O50: No | P50: 0 | Q50: 0 | R50: 0 | S50: 0 | T50: 0 | U50: Sí | V50: Sí | W50: No | X50: Sí | Y50: No | Z50: Sí | AA50: Sí | AB50: Sí | AC50: No | AD50: Sí | AE50: No | AF50: 1 | AG50: 1 | AH50: 0 | AI50: 0 | AJ50: 0 | AK50: 0 | AL50: 0 | AM50: 0 | AN50: 0 | AO50: 0 | AP50: 0 | AQ50: 0 | AR50: 5 | AS50: 2 | AT50: 4 | AU50: 3 | AV50: 1 | AW50: Presencial | AX50: 3 | AY50: 2 | AZ50: 1 | BA50: 4 | BB50: Otro | BC50: Rifas | BD50: 0
B51: Lota | C51: Biobío y Ñuble | F51: 70672725-6 | G51: Los Tilos 248-Lota | H51: 978000883 | I51: 44927 | K51: No | L51: No | M51: Sí | N51: No | O51: Sí | P51: 6 | Q51: 7 | R51: 0 | S51: 0 | T51: 0 | U51: No | V51: No | W51: No | X51: No | Y51: No | Z51: Sí | AA51: No | AB51: No | AC51: No | AD51: Sí | AE51: No | AF51: 14 | AG51: 24 | AH51: 0 | AI51: 0 | AJ51: 0 | AK51: 0 | AL51: 0 | AM51: 0 | AN51: 0 | AO51: 0 | AP51: 0 | AQ51: 0 | AR51: 3 | AS51: 1 | AT51: 2 | AU51: 4 | AV51: 5 | AW51: Presencial | AX51: S/I | AY51: S/I | AZ51: S/I | BA51: S/I | BB51: Otro | BC51: Donaciones | BD51: 0
B52: Maipú | C52: Metropolitana | F52: 70512113-3 | G52: Av. Pajaritos 1709 | H52: 99182265 | I52: 44835 | J52: Cruz Roja Maipú Oficial | K52: Sí | L52: Sí | M52: Sí | N52: Sí | O52: No | P52: 0 | Q52: 0 | R52: 0 | S52: 1 | T52: 1 | U52: No | V52: Sí | W52: Sí | X52: Sí | Y52: Sí | Z52: Sí | AA52: Sí | AB52: Sí | AC52: No | AD52: Sí | AE52: No | AF52: 0 | AG52: 0 | AH52: 0 | AI52: 0 | AJ52: 0 | AK52: 0 | AL52: 0 | AM52: 0 | AN52: 0 | AO52: 0 | AP52: 0 | AQ52: 0 | AR52: 4 | AS52: 5 | AT52: 3 | AU52: 2 | AV52: 1 | AW52: Presencial | AX52: 2 | AY52: 3 | AZ52: 1 | BA52: 4 | BB52: Policlínico | BC52: y subvención municipal | BD52: 0
B53: Mejillones | C53: Antofagasta | F53: 74818600-K | G53: Pasaje 19 de junio 910 Mejillones | H53: 990833852 | I53: 43374 | K53: No | L53: Sí | M53: Sí | N53: No | O53: Sí | P53: 7 | Q53: 23 | R53: 0 | S53: 1 | T53: 0 | U53: No | V53: No | W53: No | X53: Sí | Y53: No | Z53: Sí | AA53: Sí | AB53: Sí | AC53: No | AD53: Sí | AE53: No | AF53: 40 | AG53: 50 | AH53: 20 | AI53: 0 | AJ53: 0 | AK53: 0 | AL53: 5 | AM53: 0 | AN53: 0 | AO53: 1 | AP53: 0 | AQ53: 0 | AR53: 4 | AS53: 5 | AT53: 1 | AU53: 2 | AV53: 3 | AW53: Mixta | AX53: 4 | AY53: 2 | AZ53: 1 | BA53: 3 | BB53: Subvencíón municipal | BD53: 1
B54: Melipilla | C54: Metropolitana | F54: 70512118-4 | G54: Ortuzar 310 | H54: 228323242 | I54: 45200 | J54: @cruzroja.melipilla | K54: Sí | L54: Sí | M54: No | N54: Sí | O54: Sí | P54: 0 | Q54: 3 | R54: 0 | S54: 1 | T54: 1 | U54: No | V54: No | W54: Sí | X54: Sí | Y54: No | Z54: Sí | AA54: Sí | AB54: No | AC54: No | AD54: Sí | AE54: Sí | AF54: 80 | AG54: 110 | AH54: 70 | AI54: 1 | AJ54: 0 | AK54: 0 | AL54: 8 | AM54: 0 | AN54: 0 | AO54: 0 | AP54: 2 | AQ54: 0 | AR54: 5 | AS54: 1 | AT54: 3 | AU54: 2 | AV54: 4 | AW54: Mixta | AX54: 1 | AY54: 2 | AZ54: 3 | BA54: 4 | BB54: Arriendo | BD54: 0
B55: Molina | C55: Maule | F55: 70512100-1 | G55: Maipú 2050 Molina | H55: 752491100 | I55: 2016 | J55: @cruzroja.molina | K55: Sí | L55: Sí | M55: No | N55: Sí | O55: Sí | P55: 6 | Q55: 6 | R55: 0 | S55: 0 | T55: 0 | U55: Sí | V55: No | W55: Sí | X55: Sí | Y55: No | Z55: Sí | AA55: Sí | AB55: No | AC55: No | AD55: Sí | AE55: No | AF55: 117 | AG55: 170 | AH55: 1856 | AI55: 0 | AJ55: 0 | AK55: 0 | AL55: 0 | AM55: 1 | AN55: 0 | AO55: 0 | AP55: 0 | AQ55: 0 | AR55: 3 | AS55: 2 | AT55: 4 | AU55: 1 | AV55: 5 | AW55: Presencial | AX55: 3 | AY55: 1 | AZ55: 2 | BA55: 4 | BB55: Subvencíón municipal | BD55: 1
B56: Monte Águila | C56: Biobío y Ñuble | F56: 70672796-5 | G56: Osvaldo Cruz 148 | H56: 976992595 | I56: 44044 | K56: Sí | L56: Sí | M56: No | N56: No | O56: Sí | P56: 3 | Q56: 3 | R56: 0 | S56: 0 | T56: 0 | U56: Si | V56: No | W56: No | X56: No | Y56: No | Z56: Sí | AA56: Sí | AB56: Sí | AC56: Sí | AD56: Sí | AE56: Sí | AF56: 129 | AG56: 140 | AH56: 0 | AI56: 0 | AJ56: 0 | AK56: 0 | AL56: 0 | AM56: 0 | AN56: 0 | AO56: 0 | AP56: 0 | AQ56: 4 | AR56: 4 | AS56: 5 | AT56: 2 | AU56: 3 | AV56: 1 | AW56: Online | AX56: 3 | AY56: 4 | AZ56: 1 | BA56: 2 | BB56: Subvencíón municipal | BD56: 1
B57: Mulchén | C57: Biobío y Ñuble | F57: 70672733-7 | G57: Villagra N°110 | H57: 98809459 | I57: 45566 | K57: No | L57: No | M57: Sí | N57: No | O57: Sí | P57: 1 | Q57: 15 | R57: 0 | S57: 0 | T57: 0 | U57: Sí | V57: No | W57: No | X57: No | Y57: No | Z57: Sí | AA57: No | AB57: Sí | AC57: No | AD57: No | AE57: No | AF57: 0 | AG57: 3 | AH57: 10 | AI57: 1 | AJ57: 0 | AK57: 0 | AL57: 1 | AM57: 1 | AN57: 2 | AO57: 27 | AP57: 0 | AQ57: 0 | AR57: 3 | AS57: 2 | AT57: 4 | AU57: 1 | AV57: 5 | AW57: Online | AX57: 3 | AY57: 2 | AZ57: 1 | BA57: 4 | BB57: Arriendo | BC57: También subvención municipal | BD57: 1
B58: Nacimiento | C58: Biobío y Ñuble | F58: 70672731-0 | G58: Jorge Montt N°450 | H58: 443067732 | I58: 44743 | J58: cruz roja filial nacimiento | K58: Sí | L58: Sí | M58: No | N58: No | O58: Sí | P58: 3 | Q58: 3 | R58: 0 | S58: 0 | T58: 0 | U58: Sí | V58: Sí | W58: No | X58: No | Y58: Sí | Z58: Sí | AA58: No | AB58: Sí | AC58: No | AD58: Sí | AE58: No | AF58: 38 | AG58: 38 | AH58: 0 | AI58: 0 | AJ58: 0 | AK58: 0 | AL58: 0 | AM58: 1 | AN58: 1 | AO58: 1 | AP58: 0 | AQ58: 0 | AR58: 4 | AS58: 1 | AT58: 5 | AU58: 2 | AV58: 3 | AW58: Presencial | AX58: 3 | AY58: 2 | AZ58: 1 | BA58: 4 | BB58: Subvencíón municipal | BD58: 1
B59: Negrete | C59: Biobío y Ñuble | F59: 70676797-3 | G59: A. Moller 293 Negrete | H59: 9 5680 8744 | I59: 44805 | J59: cruzroja_negrete | K59: Sí | L59: Sí | M59: No | N59: Sí | O59: Sí | P59: 8 | Q59: 8 | R59: 0 | S59: 0 | T59: 0 | U59: No | V59: No | W59: No | X59: Sí | Y59: No | Z59: Sí | AA59: No | AB59: Sí | AC59: Sí | AD59: Sí | AE59: Sí | AF59: 60 | AG59: 200 | AH59: 500 | AI59: 0 | AJ59: 0 | AK59: 0 | AL59: 0 | AM59: 0 | AN59: 0 | AO59: 0 | AP59: 0 | AQ59: 0 | AR59: 1 | AS59: 2 | AT59: 4 | AU59: 3 | AV59: 5 | AW59: Online | AX59: 3 | AY59: 2 | AZ59: 1 | BA59: 4 | BB59: Subvencíón municipal | BD59: 1
B60: Ñuñoa | C60: Metropolitana | F60: 70512103-6 | G60: Avda. José Arrieta Nº 6068 - La Reina | H60: 982190367 | I60: 44713 | J60: @cruzrojafilialnunoa | K60: Sí | L60: Sí | M60: Sí | N60: Sí | O60: No | P60: 0 | Q60: 0 | R60: 5 | S60: 3 | T60: 2 | U60: Sí | V60: Sí | W60: No | X60: Sí | Y60: Sí | Z60: Sí | AA60: Sí | AB60: Sí | AC60: No | AD60: Sí | AE60: Sí | AF60: 95 | AG60: 10 | AH60: 95 | AI60: 0 | AJ60: 0 | AK60: 0 | AL60: 1 | AM60: 1 | AN60: 3 | AO60: 0 | AP60: 5 | AQ60: 10 | AR60: 5 | AS60: 4 | AT60: 3 | AU60: 2 | AV60: 1 | AX60: 2 | AY60: 1 | AZ60: 3 | BA60: 4 | BB60: Policlínico | BD60: 0
B61: Olmué | C61: Valparaíso | F61: 70512175-3 | G61: Henry Dunant 5318 | H61: 950772582 | I61: 45139 | K61: Sí | L61: Sí | M61: No | N61: Sí | O61: No | P61: 0 | Q61: 0 | R61: 0 | S61: 0 | T61: 0 | U61: Sí | V61: No | W61: No | X61: No | Y61: No | Z61: Sí | AA61: No | AB61: No | AC61: No | AD61: Sí | AE61: No | AF61: 18 | AG61: 12 | AH61: 4 | AI61: 0 | AJ61: 0 | AK61: 0 | AL61: 0 | AM61: 0 | AN61: 0 | AO61: 7 | AP61: 0 | AQ61: 0 | AR61: 5 | AS61: 1 | AT61: 3 | AU61: 1 | AV61: 5 | AW61: Mixta | AX61: 3 | AY61: 2 | AZ61: 1 | BA61: 4 | BB61: Arriendo | BD61: 1
B62: Osorno | C62: Los Lagos y Aysén | F62: 70672764-7 | G62: Francisco Bilbao 1438 | H62: 994448225 | I62: S/I | K62: Sí | L62: No | M62: No | N62: Sí | O62: Sí | P62: 2 | Q62: 2 | R62: 1 | S62: 0 | T62: 0 | U62: No | V62: No | W62: No | X62: Sí | Y62: No | Z62: Sí | AA62: No | AB62: No | AC62: No | AD62: No | AE62: No | AF62: 0 | AG62: 0 | AH62: 0 | AI62: 0 | AJ62: 0 | AK62: 0 | AL62: 1 | AM62: 0 | AN62: 0 | AO62: 0 | AP62: 1 | AQ62: 0 | AR62: S/I | AS62: S/I | AT62: S/I | AU62: S/I | AV62: S/I | AW62: Mixta | AX62: S/I | AY62: S/I | AZ62: S/I | BA62: S/I | BB62: Arriendo | BC62: También con Subvención municipal | BD62: 0
B63: Ovalle | C63: Atacama-Coquimbo | F63: - | G63: Socos 26 | H63: 997661179 | I63: S/I | K63: No | L63: No | M63: No | N63: No | O63: Sí | P63: S/I | Q63: S/I | R63: 0 | S63: 0 | T63: 0 | U63: No | V63: No | W63: No | X63: Sí | Y63: No | Z63: Sí | AA63: No | AB63: No | AC63: No | AD63: No | AE63: No | AF63: 0 | AG63: 0 | AH63: 0 | AI63: 0 | AJ63: 0 | AK63: 0 | AL63: 0 | AM63: 0 | AN63: 0 | AO63: 0 | AP63: 0 | AQ63: 0 | AR63: S/I | AS63: S/I | AT63: S/I | AU63: S/I | AV63: S/I | AW63: Presencial | AX63: S/I | AY63: S/I | AZ63: 1 | BA63: S/I | BB63: Arriendo | BD63: 0
B64: Parral | C64: Maule | F64: 70512158-3 | G64: Balmaceda 440 | H64: 990451670 | I64: S/I | K64: No | L64: Sí | M64: No | N64: No | O64: Sí | P64: 7 | Q64: 7 | R64: 0 | S64: 0 | T64: 0 | U64: Sí | V64: No | W64: Sí | X64: No | Y64: Sí | Z64: Sí | AA64: Sí | AB64: No | AC64: Sí | AD64: Sí | AE64: No | AF64: 120 | AG64: 96 | AH64: 200 | AI64: 2 | AJ64: 0 | AK64: 0 | AL64: 0 | AM64: 0 | AN64: 0 | AO64: 35 | AP64: 0 | AQ64: 1 | AR64: 2 | AS64: 3 | AT64: 1 | AU64: 4 | AV64: 5 | AW64: Online | AX64: 3 | AY64: 2 | AZ64: 1 | BA64: 4 | BB64: Arriendo | BD64: 1
B65: Penco | C65: Biobío y Ñuble | F65: 70672721-3 | G65: Freire 525 | H65: 432648474 | I65: 43739 | J65: cruzroja_penco | K65: Sí | L65: Sí | M65: Sí | N65: Sí | O65: Sí | P65: 10 | Q65: 4 | R65: 1 | S65: 0 | T65: 1 | U65: No | V65: No | W65: Sí | X65: Sí | Y65: No | Z65: Sí | AA65: Sí | AB65: Sí | AC65: No | AD65: Sí | AE65: No | AF65: 17 | AG65: 127 | AH65: 221 | AI65: 2 | AJ65: 0 | AK65: 0 | AL65: 0 | AM65: 2 | AN65: 2 | AO65: 155 | AP65: 0 | AQ65: 0 | AR65: 5 | AS65: 4 | AT65: 1 | AU65: 2 | AV65: 3 | AW65: Presencial | AX65: 1 | AY65: 4 | AZ65: 3 | BA65: 2 | BB65: Subvencíón municipal | BD65: 0
B66: Peñaflor Malloco | C66: Metropolitana | F66: 70512100-1 | G66: Balmaceda 803 Malloco | H66: 99554706 | I66: S/I | J66: cruzrojapenaflor | K66: Sí | L66: Sí | M66: Sí | N66: Sí | O66: Sí | P66: 4 | Q66: 14 | R66: 1 | S66: 2 | T66: 0 | U66: No | V66: No | W66: Sí | X66: Sí | Y66: Sí | Z66: No | AA66: No | AB66: Sí | AC66: No | AD66: Sí | AE66: No | AF66: 23 | AG66: 568 | AH66: 30 | AI66: 1 | AJ66: 10 | AK66: 2 | AL66: 0 | AM66: 0 | AN66: 3 | AO66: 16 | AP66: 0 | AQ66: 0 | AR66: 1 | AS66: 3 | AT66: 4 | AU66: 5 | AV66: 2 | AW66: Presencial | AX66: 3 | AY66: 2 | AZ66: 1 | BA66: 4 | BB66: Cursos PAA | BC66: Aporte de profesionales | BD66: 1
B67: Pitrufquén | C67: Araucanía | F67: 70.672.749-3 | G67: 5 de April 0585 | H67: 988864998 | I67: 45383 | K67: Sí | L67: Sí | M67: No | N67: No | O67: Sí | P67: 4 | Q67: 4 | R67: 0 | S67: 0 | T67: 0 | U67: Sí | V67: No | W67: No | X67: Sí | Y67: No | Z67: Sí | AA67: No | AB67: No | AC67: No | AD67: Sí | AE67: Sí | AF67: 8 | AG67: 0 | AH67: 13 | AI67: 0 | AJ67: 0 | AK67: 0 | AL67: 0 | AM67: 3 | AN67: 3 | AO67: 10 | AP67: 0 | AQ67: 0 | AR67: 3 | AS67: 2 | AT67: 1 | AU67: 4 | AV67: 5 | AW67: Presencial | AX67: 2 | AY67: 3 | AZ67: 1 | BA67: 4 | BB67: Subvencíón municipal | BD67: 1
B68: Playa Ancha | C68: Valparaíso | F68: 70512177-K | G68: República Esquina Municipio S/N | H68: 981203941 | I68: 45474 | K68: Sí | L68: No | M68: No | N68: No | O68: No | P68: 0 | Q68: 0 | R68: 0 | S68: 0 | T68: 0 | U68: No | V68: No | W68: No | X68: Sí | Y68: Sí | Z68: Sí | AA68: Sí | AB68: No | AC68: No | AD68: No | AE68: No | AF68: 0 | AG68: 0 | AH68: 0 | AI68: 0 | AJ68: 0 | AK68: 0 | AL68: 0 | AM68: 0 | AN68: 0 | AO68: 0 | AP68: 0 | AQ68: 0 | AR68: 1 | AS68: 2 | AT68: 3 | AU68: 5 | AV68: 4 | AW68: Presencial | AX68: 4 | AY68: 1 | AZ68: 2 | BA68: 3 | BB68: Otro | BC68: Rifas y cuotas voluntarias | BD68: 0
B69: Pozo Almonte | C69: Arica Parinacota Tarapacá | F69: 65.035.26-8 | G69: 21 de mayo 386 pzo alm. | H69: 986141117 | I69: 44927 | J69: Cruz Roja Pozo Almonte | K69: Sí | L69: Sí | M69: No | N69: Sí | O69: Sí | P69: 14 | Q69: 14 | R69: 0 | S69: 2 | T69: 0 | U69: Sí | V69: Sí | W69: Sí | X69: Sí | Y69: Sí | Z69: Sí | AA69: No | AB69: Sí | AC69: No | AD69: Sí | AE69: No | AF69: 12 | AG69: 30 | AH69: 54 | AI69: 0 | AJ69: 0 | AK69: 0 | AL69: 0 | AM69: 0 | AN69: 0 | AO69: 0 | AP69: 0 | AQ69: 1 | AR69: 1 | AS69: 3 | AT69: 5 | AU69: 2 | AV69: 4 | AW69: Online | AX69: 4 | AY69: 2 | AZ69: 1 | BA69: 3 | BB69: Otro | BC69: Rifa, Plato único | BD69: 1
B70: Providencia | C70: Metropolitana | F70: 70512102-8 | G70: 45139 | H70: 998753449 | I70: 45139 | J70: @cruzrojafilialprovidencia | K70: Sí | L70: Sí | M70: Sí | N70: No | O70: No | P70: 0 | Q70: 0 | R70: 0 | S70: 5 | T70: 1 | U70: No | V70: Sí | W70: Sí | X70: Sí | Y70: Sí | Z70: Sí | AA70: Sí | AB70: Sí | AC70: No | AD70: Sí | AE70: Sí | AF70: 52 | AG70: 22 | AH70: 0 | AI70: 5 | AJ70: 0 | AK70: 0 | AL70: 2 | AM70: 0 | AN70: 0 | AO70: 404 | AP70: 3 | AQ70: 2 | AR70: 5 | AS70: 4 | AT70: 2 | AU70: 1 | AV70: 3 | AW70: Presencial | AX70: 4 | AY70: 3 | AZ70: 2 | BA70: 1 | BB70: Arriendo | BD70: 0
B71: Pucón | C71: Araucanía | F71: 70.512.000-1 | G71: Sebastián Engler 485 | H71: 996341353 | I71: 41883 | J71: CR_PUCON | K71: Sí | L71: Sí | M71: Sí | N71: No | O71: Sí | P71: 8 | Q71: 8 | R71: 1 EIEM | S71: 0 | T71: 1 | U71: No | V71: No | W71: No | X71: No | Y71: No | Z71: No | AA71: No | AB71: Sí | AC71: No | AD71: Sí | AE71: No | AF71: 45 | AG71: 30 | AH71: 51 | AI71: 2 | AJ71: 0 | AK71: 0 | AL71: 0 | AM71: 1 | AN71: 0 | AO71: 0 | AP71: 0 | AQ71: 0 | AR71: 1 | AS71: 2 | AT71: 3 | AU71: 4 | AV71: 5 | AW71: Presencial | AX71: 4 | AY71: 3 | AZ71: 2 | BA71: 1 | BB71: Otro | BC71: aportes de los voluntarios | BD71: 0
B72: Puerto Montt | C72: Los Lagos y Aysén | F72: 70672773-6 | G72: Urmeneta 835 Puerto Montt | H72: 971006827 | I72: S/I | J72: @CRUZROJAFILIALPUERTOMONTT | K72: Sí | L72: Sí | M72: No | N72: No | O72: Sí | P72: 3 | Q72: 3 | R72: 0 | S72: 1 | T72: 1 | U72: Sí | V72: Sí | W72: No | X72: Sí | Y72: No | Z72: Sí | AA72: No | AB72: Sí | AC72: No | AD72: Sí | AE72: Sí | AF72: 38 | AG72: 0 | AH72: 71 | AI72: 23 | AJ72: 0 | AK72: 0 | AL72: 0 | AM72: 0 | AN72: 0 | AO72: 190 | AP72: 0 | AQ72: 0 | AR72: 5 | AS72: 4 | AT72: 3 | AU72: 2 | AV72: 1 | AW72: Presencial | AX72: S/I | AY72: S/I | AZ72: 1 | BA72: S/I | BB72: Arriendo | BC72: Policlínicos, Curso PAA y Subvención municipal | BD72: 0
B73: Puerto Natales | C73: Magallanes y la Antártica | F73: 70512161-3 | G73: Eberhard 298 | H73: 612411204 | I73: S/I | J73: CRUZROJAPUERTONATALES | K73: Sí | L73: No | M73: No | N73: No | O73: Sí | P73: 19 | Q73: 21 | R73: 0 | S73: 2 | T73: 0 | U73: No | V73: Sí | W73: No | X73: Sí | Y73: No | Z73: Sí | AA73: Sí | AB73: No | AC73: No | AD73: No | AE73: No | AF73: 0 | AG73: 0 | AH73: 0 | AI73: 0 | AJ73: 0 | AK73: 0 | AL73: 0 | AM73: 0 | AN73: 0 | AO73: 0 | AP73: 0 | AQ73: 0 | AR73: 1 | AS73: 5 | AT73: 2 | AU73: 3 | AV73: 4 | AW73: Presencial | AX73: 3 | AY73: 1 | AZ73: 2 | BA73: 4 | BB73: Arriendo | BD73: 0
B74: Puerto Varas | C74: Los Lagos y Aysén | F74: 70672772-8 | G74: Andrés Bello 620 | H74: 9 90898347 | I74: 44470 | J74: cruzroja_filial_puertovaras | K74: Sí | L74: Sí | M74: No | N74: No | O74: Sí | P74: 1 | Q74: 0 | R74: 0 | S74: 1 | T74: 0 | U74: Sí | V74: Sí | W74: No | X74: No | Y74: No | Z74: Sí | AA74: Sí | AB74: Sí | AC74: No | AD74: No | AE74: No | AF74: 0 | AG74: 0 | AH74: 0 | AI74: 0 | AJ74: 0 | AK74: 0 | AL74: 0 | AM74: 0 | AN74: 0 | AO74: 0 | AP74: 0 | AQ74: 0 | AR74: 1 | AS74: 2 | AT74: 3 | AU74: 4 | AV74: 5 | AW74: Online | AX74: 3 | AY74: 1 | AZ74: 2 | BA74: 4 | BB74: Arriendo | BC74: y policlinicos | BD74: 0
B75: Purén | C75: Araucanía | F75: 74795700-2 | G75: Saavedra 173 | H75: 984072300 | I75: 43739 | J75: Cruz_roja_filial_puren | K75: Sí | L75: Sí | M75: No | N75: No | O75: Sí | P75: 1 | Q75: 1 | R75: 0 | S75: 0 | T75: 0 | U75: No | V75: No | W75: No | X75: No | Y75: No | Z75: Sí | AA75: No | AB75: No | AC75: No | AD75: No | AE75: No | AF75: 5 | AG75: 167 | AH75: 0 | AI75: 0 | AJ75: 0 | AK75: 0 | AL75: 0 | AM75: 0 | AN75: 0 | AO75: 0 | AP75: 0 | AQ75: 0 | AR75: 5 | AS75: 4 | AT75: 3 | AU75: 2 | AV75: 1 | AW75: Presencial | AX75: 1 | AY75: 3 | AZ75: 2 | BA75: 4 | BB75: Otro | BC75: Eventos y cuotas | BD75: 0
B76: Quilicura | C76: Metropolitana | F76: 70672719-1 | G76: José Francisco Vergara N°318 | H76: 989599887 | I76: 44835 | J76: cruzrojafilialquilicura | K76: Sí | L76: Sí | M76: Sí | N76: No | O76: No | P76: 0 | Q76: 0 | R76: 0 | S76: 0 | T76: 0 | U76: No | V76: Sí | W76: Sí | X76: Sí | Y76: No | Z76: Sí | AA76: No | AB76: Sí | AC76: No | AD76: Sí | AE76: No | AF76: 0 | AG76: 554 | AH76: 176 | AI76: 0 | AJ76: 0 | AK76: 0 | AL76: 0 | AM76: 0 | AN76: 0 | AO76: 0 | AP76: 0 | AQ76: 0 | AR76: 1 | AS76: 4 | AT76: 2 | AU76: 3 | AV76: 5 | AW76: Online | AX76: 1 | AY76: 2 | AZ76: 3 | BA76: 4 | BB76: Policlínico | BD76: 1
B77: Quillota | C77: Valparaíso | F77: 70512171-0 | G77: La Concepción 594 | H77: S/I | I77: 45536 | J77: cruzrojafilialquillota | K77: Sí | L77: Sí | M77: No | N77: No | O77: Sí | P77: 14 | Q77: 14 | R77: 0 | S77: 0 | T77: 0 | U77: No | V77: No | W77: No | X77: Sí | Y77: Sí | Z77: Sí | AA77: No | AB77: No | AC77: No | AD77: No | AE77: No | AF77: 230 | AG77: 230 | AH77: 230 | AI77: 1 | AJ77: 2 | AK77: 0 | AL77: 0 | AM77: 0 | AN77: 0 | AO77: 0 | AP77: 0 | AQ77: 0 | AR77: 5 | AS77: 4 | AT77: 2 | AU77: 3 | AV77: 1 | AW77: Presencial | AX77: 1 | AY77: 2 | AZ77: 3 | BA77: 4 | BB77: Otro | BC77: Financiamiento voluntariado | BD77: 0
B78: Quilpué | C78: Valparaíso | F78: 70512185-0 | G78: Avenida Los Carrera 427 | H78: 951018320 | I78: dicembre 2024 | J78: CRUZROJA.QUILPUE | K78: Sí | L78: Sí | M78: No | N78: No | O78: Sí | P78: 2 | Q78: 1 | R78: 0 | S78: 1 | T78: 0 | U78: Sí | V78: Sí | W78: No | X78: Sí | Y78: Sí | Z78: No | AA78: No | AB78: No | AC78: No | AD78: Sí | AE78: No | AF78: 91 | AG78: 65 | AH78: 0 | AI78: 0 | AJ78: 0 | AK78: 0 | AL78: 0 | AM78: 0 | AN78: 0 | AO78: 80 | AP78: 0 | AQ78: 0 | AR78: 5 | AS78: 1 | AT78: 3 | AU78: 2 | AV78: 4 | AW78: Presencial | AX78: 4 | AY78: 3 | AZ78: 2 | BA78: 1 | BB78: Policlínico | BD78: 0
B79: Quintero | C79: Valparaíso | F79: 70512100-1 | G79: Av. Normandie 2110 Quintero | H79: 984903038 | I79: 45200 | K79: No | L79: Sí | M79: Sí | N79: Sí | O79: Sí | P79: 5 | Q79: 0 | R79: 0 | S79: 0 | T79: 0 | U79: Sí | V79: Sí | W79: No | X79: Sí | Y79: Sí | Z79: Sí | AA79: No | AB79: Sí | AC79: Sí | AD79: Sí | AE79: Sí | AF79: 30 | AG79: 45 | AH79: 0 | AI79: 0 | AJ79: 0 | AK79: 0 | AL79: 1 | AM79: 0 | AN79: 0 | AO79: 0 | AP79: 0 | AQ79: 0 | AR79: 2 | AS79: 1 | AT79: 3 | AU79: 5 | AV79: 4 | AW79: Presencial | AX79: 3 | AY79: 2 | AZ79: 1 | BA79: 4 | BB79: Policlínico | BC79: Arriendos y socios colaboradores | BD79: 0
B80: Rancagua | C80: Bernardo O'Higgins | F80: 70512216-5 | G80: Campos 555, Rancagua | H80: 96984881 | I80: 45597 | K80: Sí | L80: Sí | M80: No | N80: Sí | O80: No | P80: 6 | Q80: 6 | R80: 0 | S80: 0 | T80: 0 | U80: Sí | V80: No | W80: No | X80: Sí | Y80: No | Z80: No | AA80: No | AB80: No | AC80: No | AD80: No | AE80: No | AF80: 0 | AG80: 0 | AH80: 0 | AI80: 1 | AJ80: 0 | AK80: 0 | AL80: 0 | AM80: 0 | AN80: 0 | AO80: 0 | AP80: 1 | AQ80: 0 | AR80: 1 | AS80: 4 | AT80: 2 | AU80: 3 | AV80: 5 | AW80: Presencial | AX80: S/I | AY80: S/I | AZ80: S/I | BA80: S/I | BB80: Policlínico | BD80: 0
B81: Renca | C81: Metropolitana | F81: 70672720-5 | G81: José Manuel Balmaceda N°4379, Renca | H81: 976190191 | I81: 40452 | K81: Sí | L81: Sí | M81: No | N81: Sí | O81: Sí | P81: 2 | Q81: 0 | R81: 3 | S81: 0 | T81: 0 | U81: Sí | V81: No | W81: Sí | X81: Sí | Y81: No | Z81: Sí | AA81: No | AB81: No | AC81: No | AD81: No | AE81: No | AF81: 0 | AG81: 6 | AH81: 7 | AI81: 0 | AJ81: 0 | AK81: 0 | AL81: 0 | AM81: 0 | AN81: 0 | AO81: 0 | AP81: 0 | AQ81: 0 | AR81: 1 | AS81: 2 | AT81: 5 | AU81: 4 | AV81: 3 | AW81: Presencial | AX81: 3 | AY81: 1 | AZ81: 2 | BA81: 4 | BB81: Otro | BC81: Aporte diario de los profesionales | BD81: 1
B82: Reumén | C82: Los Ríos | F82: - | G82: Lautaro 204 | H82: 921960119 | I82: 44562 | J82: cruzrojareumen | K82: Sí | L82: Sí | M82: No | N82: No | O82: Sí | P82: 0 | Q82: 5 | R82: 0 | S82: 0 | T82: 0 | U82: No | V82: No | W82: No | X82: No | Y82: No | Z82: Sí | AA82: Sí | AB82: Sí | AC82: No | AD82: Sí | AE82: Sí | AF82: 2 | AG82: 120 | AH82: 4 | AI82: 0 | AJ82: 0 | AK82: 0 | AL82: 0 | AM82: 1 | AN82: 1 | AO82: 11 | AP82: 0 | AQ82: 0 | AR82: 5 | AS82: 3 | AT82: 2 | AU82: 1 | AV82: 4 | AW82: Presencial | AX82: 2 | AY82: 3 | AZ82: 1 | BA82: 4 | BB82: Otro | BC82: Ventas solidarias | BD82: 0
B83: Río Bueno | C83: Los Ríos | F83: 70672762-0 | G83: Patricio Lynch 1251 | H83: 976030312 | I83: 44621 | J83: cruzrojariobueno | K83: Sí | L83: Sí | M83: No | N83: Sí | O83: Sí | P83: 6 | Q83: 6 | R83: 0 | S83: 0 | T83: 0 | U83: No | V83: No | W83: No | X83: No | Y83: Sí | Z83: Sí | AA83: No | AB83: No | AC83: No | AD83: Sí | AE83: Sí | AF83: 240 | AG83: 240 | AH83: 30 | AI83: 0 | AJ83: 0 | AK83: 0 | AL83: 0 | AM83: 2 | AN83: 0 | AO83: 0 | AP83: 0 | AQ83: 0 | AR83: 1 | AS83: 2 | AT83: 3 | AU83: 4 | AV83: 5 | AW83: Presencial | AX83: 3 | AY83: 2 | AZ83: 1 | BA83: 4 | BB83: Arriendo | BC83: y subvención municipal | BD83: 1
B84: Salamanca | C84: Atacama-Coquimbo | F84: 72298500-1 | G84: O'higgins 321 Salamanca | H84: 996160734 | I84: 45536 | K84: Sí | L84: Sí | M84: Sí | N84: Sí | O84: Sí | P84: S/I | Q84: S/I | R84: 0 | S84: 1 | T84: 0 | U84: Sí | V84: No | W84: No | X84: No | Y84: No | Z84: No | AA84: No | AB84: No | AC84: No | AD84: No | AE84: No | AF84: 0 | AG84: 0 | AH84: 0 | AI84: 0 | AJ84: 0 | AK84: 0 | AL84: 0 | AM84: 0 | AN84: 0 | AO84: 0 | AP84: 0 | AQ84: 0 | AR84: 5 | AS84: 1 | AT84: 4 | AU84: 2 | AV84: 3 | AW84: Presencial | AX84: 3 | AY84: 4 | AZ84: 2 | BA84: 1 | BB84: Arriendo | BD84: 1
B85: San Antonio | C85: Valparaíso | F85: 70512190-7 | G85: Pedro Montt 28 | H85: 977978233 | I85: 45474 | K85: Sí | L85: No | M85: No | N85: No | O85: Sí | P85: 1 | Q85: 1 | R85: 0 | S85: 0 | T85: 1 | U85: Sí | V85: No | W85: No | X85: Sí | Y85: No | Z85: Sí | AA85: Sí | AB85: No | AC85: No | AD85: No | AE85: No | AF85: 17 | AG85: 3 | AH85: 5 | AI85: 0 | AJ85: 0 | AK85: 0 | AL85: 0 | AM85: 0 | AN85: 0 | AO85: 0 | AP85: 2 | AQ85: 0 | AR85: 4 | AS85: 3 | AT85: 2 | AU85: 1 | AV85: 5 | AW85: Presencial | AX85: 3 | AY85: 1 | AZ85: 2 | BA85: 4 | BB85: Arriendo | BC85: Policlínicos | BD85: 1
B86: San Carlos | C86: Biobío y Ñuble | F86: 70512193-1 | G86: Vicuña Mackenna 340 | H86: 984302888 | I86: 45505 | J86: Cruzrojasancarlos | K86: Sí | L86: Sí | M86: Sí | N86: No | O86: Sí | P86: 0 | Q86: 3 | R86: 0 | S86: 2 | T86: 1 | U86: Sí | V86: No | W86: Sí | X86: Sí | Y86: Sí | Z86: Sí | AA86: Sí | AB86: Sí | AC86: Sí | AD86: Sí | AE86: Sí | AF86: 208 | AG86: 208 | AH86: 32 | AI86: 2 | AJ86: 1 | AK86: 0 | AL86: 2 | AM86: 2 | AN86: 2 | AO86: 18 | AP86: 1 | AQ86: 2 | AR86: 1 | AS86: 5 | AT86: 4 | AU86: 2 | AV86: 3 | AW86: Mixta | AX86: 3 | AY86: 4 | AZ86: 1 | BA86: 2 | BB86: Arriendo | BC86: También subvención municipal | BD86: 1
B87: San Felipe | C87: Valparaíso | F87: 70512165-6 | G87: Arturo Para 11 | H87: 958210245 | I87: 40756 | K87: No | L87: Sí | M87: No | N87: No | O87: No | P87: 0 | Q87: 0 | R87: 0 | S87: 0 | T87: 0 | U87: Sí | V87: Sí | W87: Sí | X87: Sí | Y87: Sí | Z87: Sí | AA87: No | AB87: Sí | AC87: Sí | AD87: Sí | AE87: No | AF87: 190 | AG87: 120 | AH87: 5 | AI87: 0 | AJ87: 0 | AK87: 0 | AL87: 0 | AM87: 0 | AN87: 0 | AO87: 0 | AP87: 0 | AQ87: 1 | AR87: 5 | AS87: 4 | AT87: 3 | AU87: 2 | AV87: 1 | AW87: Online | AX87: 3 | AY87: 1 | AZ87: 2 | BA87: 4 | BB87: Arriendo | BD87: 0
B88: San Francisco de Mostazal | C88: Bernardo O'Higgins | F88: 70.512.123-0 | G88: Calle San Francisco N°31 | H88: 991533984 | I88: 44743 | K88: Sí | L88: Sí | M88: No | N88: Sí | O88: No | P88: 0 | Q88: 0 | R88: 1 | S88: 1 | T88: 1 | U88: Sí | V88: No | W88: Sí | X88: Sí | Y88: Sí | Z88: Sí | AA88: No | AB88: No | AC88: No | AD88: Sí | AE88: No | AF88: 298 | AG88: 0 | AH88: 0 | AI88: 0 | AJ88: 0 | AK88: 0 | AL88: 0 | AM88: 0 | AN88: 0 | AO88: 0 | AP88: 0 | AQ88: 0 | AR88: 1 | AS88: 4 | AT88: 3 | AU88: 2 | AV88: 5 | AW88: Presencial | AX88: 1 | AY88: 3 | AZ88: 2 | BA88: 4 | BB88: Arriendo | BD88: 1
B89: San José De La Mariquina | C89: Los Ríos | F89: 70672756-6 | G89: Carlos acharan 150 | H89: 969094148 | I89: 45292 | K89: Sí | L89: Sí | M89: Sí | N89: No | O89: Sí | P89: 3 | Q89: 3 | R89: 0 | S89: 0 | T89: 0 | U89: No | V89: No | W89: No | X89: Sí | Y89: No | Z89: Sí | AA89: Sí | AB89: Sí | AC89: No | AD89: No | AE89: No | AF89: 50 | AG89: 35 | AH89: 40 | AI89: 0 | AJ89: 6 | AK89: 0 | AL89: 0 | AM89: 2 | AN89: 1 | AO89: 0 | AP89: 0 | AQ89: 0 | AR89: 4 | AS89: 1 | AT89: 3 | AU89: 2 | AV89: 5 | AW89: Presencial | AX89: 1 | AY89: 2 | AZ89: 3 | BA89: 4 | BB89: Subvencíón municipal | BD89: 0
B90: San Miguel | C90: Metropolitana | F90: 70512106-0 | G90: Llano Subercaseaux 4153, San Miguel | H90: 223120066 | I90: S/I | J90: cruzroja.sanmiguel | K90: Sí | L90: Sí | M90: Sí | N90: Sí | O90: No | P90: 0 | Q90: 0 | R90: 0 | S90: 1 | T90: 3 | U90: Sí | V90: No | W90: Sí | X90: No | Y90: No | Z90: Sí | AA90: Sí | AB90: No | AC90: No | AD90: Sí | AE90: No | AF90: 314 | AG90: 122 | AH90: 54 | AI90: 2 | AJ90: 0 | AK90: 0 | AL90: 0 | AM90: 0 | AN90: 0 | AO90: 6 | AP90: 2 | AQ90: 8 | AR90: 3 | AS90: 2 | AT90: 1 | AU90: 4 | AV90: 5 | AW90: Presencial | AX90: 4 | AY90: 1 | AZ90: 2 | BA90: 3 | BB90: Subvencíón municipal | BC90: Y policlínico | BD90: 1
B91: San Pablo | C91: Los Lagos y Aysén | F91: 70672766-3 | G91: LUis Cruz 650, San Pablo | H91: 967442698 | I91: 44440 | K91: Sí | L91: Sí | M91: No | N91: Sí | O91: Sí | P91: 3 | Q91: 13 | R91: 0 | S91: 0 | T91: 0 | U91: Sí | V91: No | W91: No | X91: Sí | Y91: No | Z91: Sí | AA91: Sí | AB91: Sí | AC91: Sí | AD91: Sí | AE91: Sí | AF91: 40 | AG91: 10 | AH91: 60 | AI91: 0 | AJ91: 0 | AK91: 0 | AL91: 0 | AM91: 0 | AN91: 2 | AO91: 11 | AP91: 0 | AQ91: 0 | AR91: 4 | AS91: 1 | AT91: 5 | AU91: 3 | AV91: 2 | AW91: Presencial | AX91: 4 | AY91: S/I | AZ91: 1 | BA91: S/I | BB91: Subvencíón municipal | BD91: 0
B92: Santa Bárbara | C92: Biobío y Ñuble | F92: 70872732-9 | G92: - | H92: 969170290 | I92: 42948 | K92: No | L92: No | M92: No | N92: No | O92: Sí | P92: 10 | Q92: 13 | R92: 0 | S92: 0 | T92: 0 | U92: Sí | V92: No | W92: No | X92: Sí | Y92: No | Z92: Sí | AA92: Sí | AB92: Sí | AC92: No | AD92: No | AE92: No | AF92: 20 | AG92: 34 | AH92: 30 | AI92: 0 | AJ92: 0 | AK92: 0 | AL92: 0 | AM92: 0 | AN92: 0 | AO92: 3 | AP92: 0 | AQ92: 0 | AR92: 4 | AS92: 1 | AT92: 3 | AU92: 2 | AV92: 5 | AW92: Presencial | AX92: 4 | AY92: 2 | AZ92: 1 | BA92: 3 | BB92: Subvencíón municipal | BD92: 1
B93: Santiago Independencia | C93: Metropolitana | F93: 70512101-K | G93: Av. Independencia 339 | H93: 964670670 | I93: 45200 | J93: cruzrojasantiagoindependencia | K93: Sí | L93: Sí | M93: Sí | N93: Sí | O93: Sí | P93: 4 | Q93: 2 | R93: 2 | S93: 1 | T93: 1 | U93: No | V93: No | W93: Sí | X93: Sí | Y93: No | Z93: Sí | AA93: No | AB93: Sí | AC93: Sí | AD93: No | AE93: No | AF93: 300 | AG93: 300 | AH93: 270 | AI93: 0 | AJ93: 0 | AK93: 0 | AL93: 0 | AM93: 0 | AN93: 1 | AO93: 210 | AP93: 5 | AQ93: 0 | AR93: 5 | AS93: 3 | AT93: 2 | AU93: 1 | AV93: 4 | AW93: Mixta | AX93: 3 | AY93: 2 | AZ93: 1 | BA93: 5 | BB93: Cursos PAA | BC93: y cursos de podología | BD93: 1
B94: SR Antofagasta | C94: Antofagasta | F94: 74951300-4 | G94: Adamson 3354 | H94: 967961903 | I94: 44835 | K94: Sí | L94: Sí | M94: No | N94: Sí | O94: No | P94: 0 | Q94: 0 | R94: 0 | S94: 1 | T94: 0 | U94: No | V94: No | W94: Sí | X94: Sí | Y94: No | Z94: Sí | AA94: No | AB94: Sí | AC94: No | AD94: Sí | AE94: Sí | AF94: 0 | AG94: 0 | AH94: 0 | AI94: 1 | AJ94: 1 | AK94: 1 | AL94: 12 | AM94: 12 | AN94: 1 | AO94: 0 | AP94: 0 | AQ94: 0 | AR94: 3 | AS94: 2 | AT94: 4 | AU94: 1 | AV94: 5 | AW94: Presencial | AX94: 2 | AY94: 4 | AZ94: 1 | BA94: 3 | BB94: Otro | BC94: solo lo que aportan las filiales | BD94: 1
B95: SR Araucanía | C95: Araucanía | F95: 70672736-1 | G95: Prieto Norte 326 | H95: 975593650 | I95: 45170 | J95: @cr_araucania | K95: Sí | L95: Sí | M95: Sí | N95: No | O95: Sí | P95: 1 | Q95: 4 | R95: 2 | S95: 2 | T95: 1 | U95: No | V95: No | W95: No | X95: No | Y95: Sí | Z95: No | AA95: Sí | AB95: No | AC95: No | AD95: No | AE95: No | AF95: 0 | AG95: 1440 | AH95: 0 | AI95: 1 | AJ95: 0 | AK95: 2 | AL95: 0 | AM95: 0 | AN95: 0 | AO95: 15 | AP95: 1 | AQ95: 0 | AR95: 4 | AS95: 3 | AT95: 2 | AU95: 1 | AV95: 5 | AW95: Presencial | AX95: 1 | AY95: 3 | AZ95: 2 | BA95: 4 | BB95: Arriendo | BD95: 1
B96: SR Atacama Coquimbo | C96: Atacama-Coquimbo | F96: 73801000-0 | G96: O’Higgins 445 of 22 | H96: 512 219994 | I96: 45292 | K96: Sí | L96: Sí | M96: Sí | N96: Sí | O96: No | P96: 0 | Q96: 0 | R96: 2 | S96: 1 | T96: 1 | U96: No | V96: No | W96: No | X96: No | Y96: Sí | Z96: Sí | AA96: Sí | AB96: Sí | AC96: Sí | AD96: Sí | AE96: Sí | AF96: 0 | AG96: 0 | AH96: 20 | AI96: 2 | AJ96: 0 | AK96: 1 | AL96: 3 | AM96: 0 | AN96: 1 | AO96: 0 | AP96: 1 | AQ96: 0 | AR96: 5 | AS96: 2 | AT96: 1 | AU96: 3 | AV96: 4 | AW96: Presencial | AX96: 1 | AY96: 2 | AZ96: 3 | BA96: 4 | BB96: Arriendo | BD96: 1
B97: SR Bernardo O'Higgins | C97: Bernardo O'Higgins | F97: 65331940-1 | G97: Campos 563 Rancagua | H97: 722240204 | I97: 45017 | K97: Sí | L97: Sí | M97: No | N97: No | O97: No | P97: 0 | Q97: 0 | R97: 0 | S97: 3 | T97: 2 | U97: No | V97: No | W97: No | X97: No | Y97: Sí | Z97: Sí | AA97: Sí | AB97: Sí | AC97: No | AD97: No | AE97: No | AF97: 98 | AG97: 98 | AH97: 0 | AI97: 0 | AJ97: 0 | AK97: 0 | AL97: 2 | AM97: 0 | AN97: 1 | AO97: 0 | AP97: 1 | AQ97: 1 | AR97: 2 | AS97: 1 | AT97: 3 | AU97: 4 | AV97: 5 | AW97: Presencial | AX97: 1 | AY97: 3 | AZ97: 4 | BA97: 2 | BB97: Arriendo | BC97: Y Socios colaboradores | BD97: 1
B98: SR Biobío/Ñuble | C98: Biobío y Ñuble | F98: 70512192-3 | G98: Barros Aranas 1499 Concepción | H98: - | I98: 44470 | K98: No | L98: Sí | M98: Sí | N98: Sí | R98: 1 | S98: 3 | T98: 1 | U98: No | V98: No | W98: No | X98: No | Y98: Sí | Z98: Sí | AA98: Sí | AB98: Sí | AC98: Sí | AD98: Sí | AE98: Sí | AF98: 465 | AG98: 220 | AH98: 250 | AI98: 0 | AJ98: 0 | AK98: 0 | AL98: 0 | AM98: 0 | AN98: 0 | AO98: 0 | AP98: 0 | AQ98: 0 | AR98: S/I | AS98: S/I | AT98: S/I | AU98: S/I | AV98: S/I | AW98: Presencial | AX98: 1 | AY98: 2 | AZ98: 3 | BA98: 4 | BB98: Arriendo | BD98: 0
B99: SR Los Lagos y Aysén | C99: Los Lagos y Aysén | F99: 70672754-K | G99: Antonio Varas 214, oficina 404, puerto montt | H99: 652275827 | I99: 44470 | K99: No | L99: No | M99: Sí | N99: No | O99: No | P99: 0 | Q99: 0 | R99: 0 | S99: 1 | T99: 0 | AF99: 30 | AG99: 113 | AH99: 0 | AI99: 0 | AJ99: 0 | AK99: 0 | AL99: 0 | AM99: 0 | AN99: 0 | AO99: 0 | AP99: 1 | AQ99: 0 | AR99: 1 | AS99: S/I | AT99: S/I | AU99: 2 | AV99: S/I | AW99: Presencial | AX99: S/I | AY99: S/I | AZ99: S/I | BA99: S/I | BD99: 0
B100: SR Los Rios | C100: Los Ríos | F100: 53316538-9 | G100: Arauco 776, Valdivia | H100: 994663451 | I100: 44866 | J100: Cr_losrios | K100: Sí | L100: Sí | M100: No | N100: No | O100: No | P100: 0 | Q100: 0 | R100: 1 | S100: 1 | T100: 0 | U100: No | V100: No | W100: No | X100: Sí | Y100: Sí | Z100: Sí | AA100: Sí | AB100: Sí | AC100: No | AD100: Sí | AE100: No | AF100: 2 | AG100: 2 | AH100: 1 | AI100: 0 | AJ100: 0 | AK100: 0 | AL100: 0 | AM100: 1 | AN100: 0 | AO100: 1 | AP100: 0 | AQ100: 0 | AR100: 1 | AS100: 2 | AT100: 3 | AU100: 4 | AV100: 5 | AW100: Presencial | AX100: 2 | AY100: 1 | AZ100: 3 | BA100: 4 | BB100: Arriendo | BC100: Y subvención municipal | BD100: 1
...

Sheet Sugerencias
A1: Filial | B1: Comentario
A2: Almendral | B2: S/I
A3: Angol | B3: S/I
A4: Antofagasta | B4: Como sugerencia sería implementar en base a la transparencia e igualdad que el Gobierno y la Junta para los cursosvenideros con fondos internacionales sean más participativos; es decir que sea con una postulación a nivel nacional y no elegidos por comités o Direcciones Nacionales, esto en base a que estoy seguro que dentro del voluntariado a nivel Nacional existe más de una persona con las competencia para que pueda adquirir los conocimientos de dicho curso; me baso en que vemos que asisten a cursos a nivel internacional y no se tiene mayor información de lo expuesto, quizás la retroalimentación la obtiene la filial o comité al cual pertenece el voluntario pero para la mayor igualdad sería bueno que estos conocimientos sean compartidos a través de una plataforma virtual para que todo el voluntariado a nivel nacional lo pueda adquirir.
A5: Arica y Parinacota | B5: S/I
A6: Bulnes | B6: NOSOTROS COMO FILIAL BULNES NECESITAMOS MAYOR APOYO EN LAS GESTIONES , PARA PODER ADMINISTRAR DE MEJOR FORMA EL HOGAR DE ANCIANOS, YA QUE ESTAMOS OFRECIENDO UNA LABOR EN LA COMUNIDAD PARA LAS PERSONAS MAYORES VULNERBLES ABANDONADAS POR LA FAMILIA Y SOCIEDAD,TENEMOS PRESENCIA,CREDIBILIDAD , CONFIABILIDAD,DEJANDO BIEN A LA INSTITUCION , PERO LOS RECURSOS QUE HACEN POCOS, SE REQUIERE APOYO DEL NIVEL CENTRAL, SIEMPRE ESTAMOS NECESITANDO RECURSOS ECONOMICOS, ALIMENTOS, VESTUARIOS IMPLEMENTOS PARA EL FUNCIONAMNIENTO.EL MUNICIPIO HA SIDO UN GRAN APOYO PERO NO ES SUFIECIENTE ENE STOS TIEMPOOS YA QUE SE REQUIERE UN POCO MAS.- Muchas veces nos sentimos SOLAS y sin apoyo Pero no podemos dejar de agradecer al comité regional Bio Bio-Ñuble ,por el apoyo permanente, cuando pueden hacerlo.- Si se necesita el respaldo COMITÉ CENTRAL EN GESTIONES IMPORTANTES,Y APOYO ECONOMICO, marerial
A7: Cabrero | B7: Siempre orgullosos y orgullosas del trabajo realizado y de pertenecer a esta hermosa y loable institución. Por nuestra parte sugerimos una acceso para amplio y fácil a poder capacitar a nuestros voluntarios y voluntarias en primeros auxilios por voluntarios del área de la salud, que pudiesen no contar con título de instructoría desde CR, pero si conocimientos del área por ámbito profesional, eso facilitaría este proceso sobre todo pensando en que ya es complejo poder contar con disponibilidad para participar activamente de actividades de filial, es aún más complejo poder asistir a otros lugares a capacitarse , por disponibilidad de tiempo, económica, etc.
A8: Caldera | B8: S/I
A9: Cañete | B9: S/I
A10: Capitán Pastene | B10: Nuestra Filial se encuentra en un lugar apartado de los centros urbanos más importantes de la región de La Araucanía. Esto ha dificultado la posibilidad de recibir la formación en Primeros Auxilios y Doctrina Institucional, principalmente. Aún así, nos hemos integrado a campañas y actividades regionales y nacionales. También hemos sido referente y centro de operaciones durante los incendios en que recibimos la intervención del Proyecto DREF. En cuanto a financiamiento, la colecta anual en la semana de Cruz Roja, es muy importante para financiar actividades y generar ayudas que entregamos a la comunidad consistente, principalmente, en medicamentos, alimentos especiales, exámenes médicos, canastas familiares, etc. Nuestros ingresos se obtienen mediante la participación en Ferias Gastronómicas de comidas italianas. Esto es una vez al año y lo que ofrecemos es confeccionado por el voluntariado. Adolecemos de conocimientos y expertis en tecnología, lo que hace difícil la entrega de Balance y Memoria Anual. Toda la documentación que requiere esta destreza nos significa una dificultad, la que salvamos con ayuda externa de personas de buena voluntad, asumiendo la responsabilidad que nos asiste como Cruces Rojas comprometidas con nuestra querida Institución.
A11: Carahue | B11: - CAPACITACION COMPUTACIONAL GENERAL. - CAPACITACION EN BALANCES. - ETICA Y DOCTRINA.
A12: Cartagena | B12: CAPACITACION EN FILIAL O ZONA COSTA POR TIEMPO Y COSTOS. (PRESENCIAL DESDE SEDE CENTRAL A FILIAL)
... A113: Yungay | B113: APOYAR LAS FILIALES PARA PODER GESTIONAR DIFERENTES PROYECTO, SUBVENCIONES, ETC. PARA SI PODER TENER MAYOR CONOCIMIENTOS DE ESTOS Y PODER CONSERVAR Y ARREGLAR LAS FILIALES.

Sheet Validación formularios
C2: Sede Regional | D2: Presidente | E2: Fono Sede | F2: Fono Celular | G2: Correo electrónico | H2: Memoria regional | J2: Alto Hospicio | K2: =VLOOKUP(J2,'Datos filial'!$B$2:$B$148,1,0) -> #N/A | L2: =IF(K2=J2,"OK","NOK") -> #N/A | M2: en receso
B3: XV-I | C3: Arica Parinacota Tarapacá | D3: Berta Aravena Bustamante | E3: 57 - 2344939 | F3: 569 88895009 | G3: regional.primera@cruzroja.cl | J3: Lautaro | K3: =VLOOKUP(J3,'Datos filial'!$B$2:$B$148,1,0) -> #N/A | L3: =IF(K3=J3,"OK","NOK") -> #N/A | M3: En receso
B4: II | C4: Antofagasta | D4: Héctor Castillo | E4: 55 - 2847328 | F4: 569 67961903 | G4: regional.segunda@cruzroja.cl | H4: OK | J4: Freire | K4: =VLOOKUP(J4,'Datos filial'!$B$2:$B$148,1,0) -> #N/A | L4: =IF(K4=J4,"OK","NOK") -> #N/A | M4: Cerrada
B5: III-IV | C5: Atacama-Coquimbo | D5: Virginia Frías Bulo | E5: 51 - 2219994 | F5: 569 92400633 | G5: regional.tercera@cruzroja.cl | H5: OK | J5: Teodoro Schmidt | K5: =VLOOKUP(J5,'Datos filial'!$B$2:$B$148,1,0) -> #N/A | L5: =IF(K5=J5,"OK","NOK") -> #N/A | M5: Cerrada
B6: V | C6: Valparaíso | D6: Cecilia Pedreros Barrera | E6: 32 - 2883307 | F6: 569 99987499 | G6: regional.quinta@cruzroja.cl | H6: OK | J6: Puerto Aysén | K6: =VLOOKUP(J6,'Datos filial'!$B$2:$B$148,1,0) -> #N/A | L6: =IF(K6=J6,"OK","NOK") -> #N/A | M6: Cerrada
B7: VI | C7: Bernardo O'Higgins | D7: Raquel Oyarzún Reyes | E7: 72 - 2240204 | F7: 569 81370465 | G7: regional.sexta@cruzroja.cl | H7: OK
B8: VII | C8: Maule | D8: Juana Barraza Gaete | E8: 71 - 2211994 | F8: 569 68985175 | G8: regional.septima@cruzroja.cl
B9: VIII-XVI | C9: Biobío y Ñuble | D9: Rosa Barrera Muñoz | E9: 41 - 2223367 | F9: 569 98328323 | G9: regional.octava@cruzroja.cl | H9: OK
B10: IX | C10: Araucanía | D10: Mariela Erices Labrin | E10: 45 - 2216715 | F10: 569 75593650 | G10: regional.novena@cruzroja.cl | H10: OK
B11: XIV | C11: Los Ríos | D11: Marisol Córdova Medina | E11: 63 - 2219709 | F11: 569 94663451 | G11: regional.losrios@cruzroja.cl | H11: OK
B12: X-XI | C12: Los Lagos y Aysén | D12: Silvia Muñoz Muñoz | E12: 65 - 2275827 | F12: 569 85830557 | G12: regional.decima@cruzroja.cl | H12: OK
B13: XII | C13: Magallanes y la Antártica | D13: María Luisa Cárcamo Barrientos | E13: 61 - 2228669 | F13: 569 88678879 | G13: regional.duodecima@cruzroja.cl
B14: RM | C14: Metropolitana | D14: No aplica
G15: Suma recibidos | H15: =COUNTA(H3:H14) -> 8
B16: Filial Original | C16: Filial recibida
A17: 1 | B17: Almendral | C17: =VLOOKUP(B17,'Datos filial'!$B$2:$B$148,1,0) -> Almendral | D17: =IF(C17=B17,"OK","NOK") -> OK
A18: 2 | B18: Ancud | C18: =VLOOKUP(B18,'Datos filial'!$B$2:$B$148,1,0) -> Ancud | D18: =IF(C18=B18,"OK","NOK") -> OK
A19: 3 | B19: Angol | C19: =VLOOKUP(B19,'Datos filial'!$B$2:$B$148,1,0) -> Angol | D19: =IF(C19=B19,"OK","NOK") -> OK
A20: 4 | B20: Antofagasta | C20: =VLOOKUP(B20,'Datos filial'!$B$2:$B$148,1,0) -> Antofagasta | D20: =IF(C20=B20,"OK","NOK") -> OK
A21: 5 | B21: Arica y Parinacota | C21: =VLOOKUP(B21,'Datos filial'!$B$2:$B$148,1,0) -> Arica y Parinacota | D21: =IF(C21=B21,"OK","NOK") -> OK
A22: 6 | B22: Bulnes | C22: =VLOOKUP(B22,'Datos filial'!$B$2:$B$148,1,0) -> Bulnes | D22: =IF(C22=B22,"OK","NOK") -> OK
A23: 7 | B23: Cabrero | C23: =VLOOKUP(B23,'Datos filial'!$B$2:$B$148,1,0) -> Cabrero | D23: =IF(C23=B23,"OK","NOK") -> OK
A24: 8 | B24: Caldera | C24: =VLOOKUP(B24,'Datos filial'!$B$2:$B$148,1,0) -> Caldera | D24: =IF(C24=B24,"OK","NOK") -> OK
A25: 9 | B25: Cañete | C25: =VLOOKUP(B25,'Datos filial'!$B$2:$B$148,1,0) -> Cañete | D25: =IF(C25=B25,"OK","NOK") -> OK
A26: 10 | B26: Capitán Pastene | C26: =VLOOKUP(B26,'Datos filial'!$B$2:$B$148,1,0) -> Capitán Pastene | D26: =IF(C26=B26,"OK","NOK") -> OK
A27: 11 | B27: Carahue | C27: =VLOOKUP(B27,'Datos filial'!$B$2:$B$148,1,0) -> Carahue | D27: =IF(C27=B27,"OK","NOK") -> OK
A28: 12 | B28: Cartagena | C28: =VLOOKUP(B28,'Datos filial'!$B$2:$B$148,1,0) -> Cartagena | D28: =IF(C28=B28,"OK","NOK") -> OK
... A160: 144 | B160: Yungay | C160: =VLOOKUP(B160,'Datos filial'!$B$2:$B$148,1,0) -> Yungay | D160: =IF(C160=B160,"OK","NOK") -> OK
C161: Recibidos filial | D161: =COUNTIF(D17:D160,"OK") -> 131
C162: Recibidos Sede regional | D162: =H15 -> 8
C163: Total recibidos | D163: =SUM(D161:D162) -> 139
C164: Total esperado | D164: =A160+11 -> 155
C165: % cumplimiento | D165: =D163/D164 -> 0.89677419

Sheet Campos desplegables
A3: Cargos | B3: Género | C3: Tipo Voluntario | D3: Financiamiento | E3: Capacitación | F3: Binario
A4: Presidente | B4: F | C4: Activo | D4: Arriendo | E4: Online | F4: Sí
A5: Vicepresidente | B5: M | C5: Llamada | D5: Policlínico | E5: Presencial | F5: No
A6: Secretario/a | B6: Otro | C6: Otro | D6: Cursos PAA | E6: Mixta
A7: Director/a de Desarrollo | D7: Subvencíón municipal
A8: Director/a de Finanzas | D8: Otro
A9: Director/a de Salud
A10: Director/a de Comunicaciones
A11: Director/a de Juventud
A12: Director/a de Bienestar social
A13: Director/a de Gestión del Riesgo
A14: Voluntario/a
